{"222535": [{"id": "7w8ny8jC7EtDyl5g35JmZX", "tf": 1}], "222538": [{"id": "4U9uKCsD9hqmOFVlraX41a", "tf": 1}], "222540": [{"id": "2FpyKkCFIfqmp6eQx4Rn1V", "tf": 1}], "222560": [{"id": "0NXQ8VCPViY9CbIT2w5t5N", "tf": 1}], "222563": [{"id": "6q93Jau7PPkZQG3YOf36Tz", "tf": 1}], "222573": [{"id": "1usmQnyxf91JTKRjIBFvGj", "tf": 1}], "222581": [{"id": "133W87XUq6un325yz5BTpq", "tf": 1}], "222587": [{"id": "7oK9VyNzrYvRFo7nQEYkWN", "tf": 1}], "222600": [{"id": "32SmDHzbqYRAhX9Jq4gDnT", "tf": 1}, {"id": "57RKxckEkdbK7QXbN2ufzp", "tf": 1}, {"id": "5F9Pe2Tg20NRi8N4cHHXUD", "tf": 1}], "222613": [{"id": "0s1PewZjIU8DJqxktjeZaX", "tf": 1}], "222621": [{"id": "45ZGEdLxCZvdMX9jWlsAAx", "tf": 1}], "222627": [{"id": "3OIoy3TNU7CL5PTaHOGmbR", "tf": 1}], "222640": [{"id": "0d28khcov6AiegSCpG5TuT", "tf": 1}], "222653": [{"id": "6kPJZM97LwdG9QIsT7khp6", "tf": 1}], "222657": [{"id": "3fS0GCbLTLK59MYn7HYMNi", "tf": 1}], "222667": [{"id": "0UUSebzzrC8hKiVcX8fBsz", "tf": 1}], "222680": [{"id": "67L03LeXeZ73X7opELnh5P", "tf": 1}], "222693": [{"id": "4uCRg4dM7mnDvJgdTm5pBB", "tf": 1}], "222707": [{"id": "39pS70eeDvyCAF3t8NAlVV", "tf": 1}, {"id": "3KYiA4vq6RPO1dE2XROXd8", "tf": 1}, {"id": "3NuK5xMlSlB6K2Qp16zf3h", "tf": 1}], "222720": [{"id": "1mYcQvtPBNqhFKMK36Ok0l", "tf": 1}], "222731": [{"id": "4XP6qLtHI0n9UjIPTsuqe8", "tf": 1}], "222732": [{"id": "2AIWoHr9DF6y4KALCBKWQS", "tf": 1}], "222733": [{"id": "2aFsfzUuXuxDr4xo8ndfUt", "tf": 1}, {"id": "6i8ecOsx4J2Px1maiqzqoG", "tf": 1}], "222747": [{"id": "3DdCb7EyPUcUD0LKWkJ0L7", "tf": 1}], "222760": [{"id": "0xuXRQJfxmdP6gvfDe2Z4L", "tf": 1}, {"id": "38DmpKGMulBN5NuXCZopOF", "tf": 1}, {"id": "4o1E2c0ye1RlIJJqOM0dqP", "tf": 1}, {"id": "6P4uWkUqr0M6eVYjmbKdAf", "tf": 1}], "222768": [{"id": "71nvXPQMmYflxqil6Q9ehh", "tf": 1}], "222770": [{"id": "7ouItOD31hjhdOYeIBcQaR", "tf": 1}], "222773": [{"id": "26Hu22OnPChPeK3II0J1Tt", "tf": 1}], "222777": [{"id": "4WuYrtIkVR8vTE0nBJwnJX", "tf": 1}], "222787": [{"id": "0ifLplTQxXkFZKMQpWCHii", "tf": 1}, {"id": "5lNuqFVMca4vPupY10cH0J", "tf": 1}], "222798": [{"id": "4pP59HlzHAwxIynUHCegzv", "tf": 1}], "222800": [{"id": "2PKiB1i2DwG2npY2xxjLnE", "tf": 1}], "222821": [{"id": "4xh4WZodJ7NpFi7zKgiW3q", "tf": 1}], "222827": [{"id": "3rtxFFGZ10e2vYBo7PsPf2", "tf": 1}], "222853": [{"id": "61XUS0rxs5k6H0mtgAWKnm", "tf": 1}], "222857": [{"id": "20WcuVfTh0QFkIsJUncdON", "tf": 1}, {"id": "4mm8Ia1SKncoc2CKN5OEhN", "tf": 1}], "222866": [{"id": "447yWcDPg1ddgcHBLGpJC0", "tf": 1}, {"id": "7n1940b6kHcaEewFSZXnXa", "tf": 1}], "222867": [{"id": "0pdeEwJuUMcBfmoeAMktcf", "tf": 1}, {"id": "3E2jVBZU7fjRNB0m3PrrhF", "tf": 1}, {"id": "4aODvtjwLMcNQ8x1xCw0uy", "tf": 1}], "222880": [{"id": "0arItEjl5jRh5FE7zyrv4A", "tf": 1}], "222890": [{"id": "2EHVjRFRSsXQaHAsys74Us", "tf": 1}], "222920": [{"id": "5hlWtrnVUyAze5WkxF9P56", "tf": 1}, {"id": "60jzFy6Nn4M0iD1d94oteF", "tf": 1}], "222933": [{"id": "2p9sprAX27D6U5cuSE9NsM", "tf": 1}], "222936": [{"id": "0Aergaee1PD3zbWcjxcUJl", "tf": 1}], "222960": [{"id": "2ZMI0QNoqU9fQZFirR9WpK", "tf": 1}, {"id": "6QFIhhGf2T54UzNlVb2eee", "tf": 1}], "222961": [{"id": "2W4smyeMF0Zhr2KZhAsl99", "tf": 1}], "222987": [{"id": "036GQb6SETOJJG8BxJTNxc", "tf": 1}, {"id": "63iZvr19gFAToQJdY7Sysn", "tf": 1}], "222997": [{"id": "1iSqfoUFnQwV0QW1EfUit8", "tf": 1}], "222b3aljxx6ffwkmfjub": [{"id": "222B3aljXx6fFwKmFjuBED", "tf": 1}], "222nc9tkxkhfz2gbropwh3": [{"id": "036GQb6SETOJJG8BxJTNxc", "tf": 1}, {"id": "0aOluBqXYd0rFSCsgDyAWX", "tf": 1}, {"id": "0kzw2tRyuL9rzipi5ntlIy", "tf": 1}, {"id": "0lYS1tJg3r6ATe9bRPB0Hu", "tf": 1}, {"id": "0mUyMawtxj1CJ76kn9gIZK", "tf": 1}, {"id": "0qcr5FMsEO85NAQjrlDRKo", "tf": 1}, {"id": "0tBbt8CrmxbjRP0pueQkyU", "tf": 1}, {"id": "0TDLuuLlV54CkRRUOahJb4", "tf": 1}, {"id": "10GJQkjRJcZhGTLagFOC62", "tf": 1}, {"id": "19hh7DkfRBrpRGYfKlw7jb", "tf": 1}, {"id": "1awcbkmzafwSmo0cgyMFio", "tf": 1}, {"id": "1HNkqx9Ahdgi1Ixy2xkKkL", "tf": 1}, {"id": "1qDrWA6lyx8cLECdZE7TV7", "tf": 1}, {"id": "1rfofaqEpACxVEHIZBJe6W", "tf": 1}, {"id": "1sYSP7gKa5kdKIfhANfori", "tf": 1}, {"id": "1u8c2t2Cy7UBoG4ArRcF5g", "tf": 1}, {"id": "24lMtPOCzP5g4hrg3NklLa", "tf": 1}, {"id": "2cOUlop2ZakjOKe4WinesN", "tf": 1}, {"id": "2DpCdPMg1BADE4HDnxt3Rd", "tf": 1}, {"id": "2fZQIJew3nkNe99s2PKzul", "tf": 1}, {"id": "2MfOcbtgz2yTsiznFmVZUN", "tf": 1}, {"id": "2qT1uLXPVPzGgFOx4jtEuo", "tf": 1}, {"id": "2zFF6jG5hQArbzcXz3KUWk", "tf": 1}, {"id": "34oB5r0lcN3fYWCs2uA1k5", "tf": 1}, {"id": "3C0nOe05EIt1390bVABLyN", "tf": 1}, {"id": "3cfOd4CMv2snFaKAnMdnvK", "tf": 1}, {"id": "3dYD57lRAUcMHufyqn9GcI", "tf": 1}, {"id": "3e9HZxeyfWwjeyPAMmWSSQ", "tf": 1}, {"id": "3KkXRkHbMCARz0aVfEt68P", "tf": 1}, {"id": "3OtMnyUaiipcAT23A8liyi", "tf": 1}, {"id": "3QGsuHI8jO1Rx4JWLUh9jd", "tf": 1}, {"id": "3qRHCvn70YpVFFkx3lrAYf", "tf": 1}, {"id": "3zkWCteF82vJwv0hRLba76", "tf": 1}, {"id": "49FYlytm3dAAraYgpoJZux", "tf": 1}, {"id": "4RCWB3V8V0dignt99LZ8vH", "tf": 1}, {"id": "4Ro98RCK90oHqqSZUnTFq5", "tf": 1}, {"id": "59mrqUmhpmcfUns8BKkV30", "tf": 1}, {"id": "5EbX5xL3O2xT8FxCpYzgUO", "tf": 1}, {"id": "5eWgDlp3k6Tb5RD8690s6I", "tf": 1}, {"id": "5Hroj5K7vLpIG4FNCRIjbP", "tf": 1}, {"id": "5jrdCoLpJSvHHorevXBATy", "tf": 1}, {"id": "5T7ZFtCcOgkpjxcuaeZbw0", "tf": 1}, {"id": "5uCax9HTNlzGybIStD3vDh", "tf": 1}, {"id": "5unfeZUhKhICP73CDYBW4N", "tf": 1}, {"id": "5YhAAlelWek228jZzxgEfr", "tf": 1}, {"id": "6e40mgJiCid5HRAGrbpGA6", "tf": 1}, {"id": "6GzApXoBQiiAjak3tOQfV3", "tf": 1}, {"id": "6QicTxeiSaRkPnkGDUvYOs", "tf": 1}, {"id": "6tXjP6xgPJ7Xr1igrO6bOE", "tf": 1}, {"id": "6ZANrVuAMp2rpjhfbOuJly", "tf": 1}, {"id": "7fa9MBXhVfQ8P8Df9OEbD8", "tf": 1}, {"id": "7iyKbBjb2fmTnTfCjCh7ER", "tf": 1}, {"id": "7uolkTLavH97itenLjNmx9", "tf": 1}, {"id": "7xoUc6faLbCqZO6fQEYprd", "tf": 1}], "223": [{"id": "4JDZl9nKIAhAhDjw753u4X", "tf": 2}], "223000": [{"id": "0YHI5hydPPth6J5UOzdLDX", "tf": 1}, {"id": "1GJLqaSf3YAHzHlnrFjeCS", "tf": 1}, {"id": "1qm9MfTAoEixNPSqshHqfV", "tf": 1}, {"id": "2L1CvihtseniGV9XsDnNZj", "tf": 1}, {"id": "3dFwpxh2yH7C7p9BGEKLVB", "tf": 1}, {"id": "6lruHh1jF7ezgbLv72xYmf", "tf": 1}], "223004": [{"id": "4xjgqApMW2Z2Eh1LC0i1tC", "tf": 1}], "223027": [{"id": "0Y0JVqSlj8J512B5kjKekP", "tf": 1}, {"id": "1Km67XnxHrmFchlhwI7kKr", "tf": 1}, {"id": "5tzr9EB0ZUToxk79Q9mVkP", "tf": 1}], "223045": [{"id": "020wG4EHTwBy5h2rbpxqvK", "tf": 1}], "223053": [{"id": "2fTsFCKRFQ5M0igJgabnLA", "tf": 1}], "223067": [{"id": "0lOe1dR2TNkJMCjIcRuw6T", "tf": 1}, {"id": "0zp92Miwhh5vO3B3dhxrxI", "tf": 1}, {"id": "5VRxcsBgrwQj4naQHU2kM6", "tf": 1}], "223080": [{"id": "3Rx0EJrqN0EDoy20YVxQfv", "tf": 1}], "223082": [{"id": "5Dg2h1wsm7ZijCo0yLmbvR", "tf": 1}], "223086": [{"id": "4uZwCUcyuwBxvG4G2CsNq5", "tf": 1}], "223089": [{"id": "17DiAfqZlhE4RkDlx0UTM1", "tf": 1}], "223107": [{"id": "2RqtfcLB7iOZj0zYB8Auhu", "tf": 1}], "223120": [{"id": "2c32F1jt47FbgVmJXwkDGq", "tf": 1}], "223123": [{"id": "5SE57ljOIUJ1ybL9U6CuBH", "tf": 1}], "223133": [{"id": "15taea6JZLAfG5OX0pzfG6", "tf": 1}], "223140": [{"id": "5M9jOReAKGZ2AttVefFjTY", "tf": 1}], "223147": [{"id": "0I7EJmk6S47mpVh73dB02r", "tf": 1}, {"id": "1MTMedlCphum6mRcd8YzvE", "tf": 1}, {"id": "3pWcj8hxj3fsb9TDAcMpEl", "tf": 1}, {"id": "4kT9iDGAQt83gOUdbTUtaW", "tf": 1}, {"id": "61lqNlVRnWYiR9C7BDJw2l", "tf": 1}, {"id": "7iaw359G2XT14uTfV9feip", "tf": 1}], "223187": [{"id": "1leXuBiWQMgbvOIIedqbLB", "tf": 1}, {"id": "5masKPHeAOVNgxdLebIcK7", "tf": 1}, {"id": "6Y6YC93R1r0CISm5iC4j27", "tf": 1}], "223190": [{"id": "6XOYVSmNDjKUNMXooU4s4z", "tf": 1}], "223200": [{"id": "2bPujZTjHKSIHztskmfudg", "tf": 1}], "223234": [{"id": "4SRtBFocTtcaWP3etJb7GK", "tf": 1}], "223240": [{"id": "4h4aAvqiftNLS5XeookGx1", "tf": 1}], "223253": [{"id": "1SRkKyJ2JjMZgyDWC30zKv", "tf": 1}, {"id": "2tJulUYLDKOg9XrtVkMgcJ", "tf": 1}, {"id": "4lLtanYk6tkMvooU0tWzG8", "tf": 1}], "223256": [{"id": "20JtELGPfOAMq7FpUt8eSM", "tf": 1}], "223258": [{"id": "2W4yABdLc4Jnds67Poi5Nl", "tf": 1}], "223264": [{"id": "4HujwzHGxXQ9BkrqW3lIfJ", "tf": 1}], "223293": [{"id": "3yuJVbCLjxcu0T6bZoiWXg", "tf": 1}], "223299": [{"id": "4lKXjLzAV0Nxwln8MxHVtQ", "tf": 1}], "223304": [{"id": "4XuPsbwMAzfmaUfjEsoyiO", "tf": 1}], "223312": [{"id": "1EfbXCeMYyLHNwAK4cRgQ2", "tf": 1}], "223320": [{"id": "0fMdbQrsYylKuCFYldizco", "tf": 1}, {"id": "4TIa51S5pZ7U9UdqHWqvsx", "tf": 1}], "223333": [{"id": "63xBnyUVKIupzjHno4wFs3", "tf": 1}, {"id": "6Qg7cgN1oZ5mG5nZe9UG0X", "tf": 1}], "223338": [{"id": "6Pkqfsx6tipFO4qpwkuRYz", "tf": 1}], "223357": [{"id": "08vJxMYhmZu6YTWqVmLgrA", "tf": 1}], "223360": [{"id": "3qAqWMAacEDWKuI9pMfhRm", "tf": 1}], "223385": [{"id": "17arbOEI0m070vJ9ILOmAR", "tf": 1}], "223387": [{"id": "1zZvPumuScWPZKZOCC6yq0", "tf": 1}], "223400": [{"id": "7nDFTHHwfe32a8qdp9XqPy", "tf": 1}], "223413": [{"id": "5bcTCxgc7xVfSaMV3RuVke", "tf": 1}, {"id": "6BaCraQ9xeLYg4Sb9TBT2X", "tf": 1}], "223425": [{"id": "7ude1FCZiruFR5yyYH7DUD", "tf": 1}], "223440": [{"id": "2uXewDKMktNkkMfotqSxN6", "tf": 1}, {"id": "437h9GRi70A1BzMzh4cyra", "tf": 1}, {"id": "68vgtRHr7iZHpzGpon6Jlo", "tf": 1}], "223448": [{"id": "6mNMp0g3zkg1K7uBpn07zl", "tf": 1}], "223467": [{"id": "6TpowNTagUJ7f8ctFFCVN8", "tf": 1}], "223469": [{"id": "7dFikRPQuLFz4PdCw4ZvCy", "tf": 1}], "223480": [{"id": "4nK5YrxbMGZstTLbvj6Gxw", "tf": 1}], "223493": [{"id": "1nAGuIZXz6vb8XW0xiMqic", "tf": 1}, {"id": "5PZvQeHocidnZ73a3pHO76", "tf": 1}], "223500": [{"id": "6yllTYSMEmOagRltq1VlsP", "tf": 1}], "223504": [{"id": "1louJpMmzEicAn7lzDalPW", "tf": 1}], "223507": [{"id": "0CMRCkUdmiHGt7EzEUIskU", "tf": 1}, {"id": "2cYZpcIV39X48RnOFM7w2V", "tf": 1}, {"id": "31ZkEyJlfJtCjyMhmZxLEd", "tf": 1}], "223520": [{"id": "5yEwEUGYpCWsSOC0rm8gFJ", "tf": 1}, {"id": "6Qp0IqPJEgQt3fKjaCRq1w", "tf": 1}], "223523": [{"id": "5PYQUBXc7NYeI1obMKSJK0", "tf": 1}], "223533": [{"id": "0byab45cmZntz74RxcASrf", "tf": 1}, {"id": "10fddGyyeUquZZ2uPTjD7P", "tf": 1}, {"id": "3hc7PLcmuZbJGPjhIore1i", "tf": 1}, {"id": "5mYNWSc1AE7pWS3Ax4e8Dl", "tf": 1}, {"id": "5zXPfLfG8lpiwk8UqXKUlQ", "tf": 1}], "223546": [{"id": "6F5c58TMEs1byxUstkzVeM", "tf": 1}], "223547": [{"id": "5KSJ9k1FYjFLnIRlJT2wF8", "tf": 1}], "223548": [{"id": "6KxWEKZT63q9ioV38MuZxZ", "tf": 1}], "223552": [{"id": "6ZifCCNZnqWrtIeBp7RWP9", "tf": 1}], "223553": [{"id": "31mqc7EKPsJf3pe6H5jEfC", "tf": 1}], "223573": [{"id": "7DBIvPoaC3Wv69Qe5II7b3", "tf": 1}], "223587": [{"id": "51uLQESb4VnYAbs5WtGxho", "tf": 1}], "223590": [{"id": "52AWuNH7rgcyRdEM0lQzPz", "tf": 1}], "223592": [{"id": "3zzDs7euxA9c5guPOt7A1B", "tf": 1}], "223600": [{"id": "2IqjKEBiz0CdLKdkXhxw84", "tf": 1}, {"id": "2ZMafcgiEaAx90bNT3mFiI", "tf": 1}], "223602": [{"id": "6RgdRnDR2dvG5s5o6pJIgk", "tf": 1}], "223613": [{"id": "07GvNcU1WdyZJq3XxP0kZa", "tf": 1}, {"id": "4xh7W7tlNMIczFhupCPniY", "tf": 1}, {"id": "5i50gKdLAjjIr7UxRT5IVy", "tf": 1}, {"id": "5TtUpDKB0bVmzK543eANFp", "tf": 1}], "223620": [{"id": "4kRT3cCwp0uYEqh4hHvxZS", "tf": 1}], "223627": [{"id": "7cpEhtddPd70q9a48mRvgz", "tf": 1}], "223640": [{"id": "32vbyo69yJq5WXyvHCF0Yp", "tf": 1}], "223655": [{"id": "7rGN3oqzCpG2mLcwoPwDQm", "tf": 1}], "223667": [{"id": "6hnCx2jmD0RPkbtzUXSBn4", "tf": 1}], "223680": [{"id": "4c2Zdtqy5x9BkhTSJRTDmk", "tf": 1}], "223683": [{"id": "5KdOgQ3VAK05QrGC98X9ta", "tf": 1}], "223693": [{"id": "6j4eSvLSgkb3ehJksCtq3w", "tf": 1}], "223694": [{"id": "3ydfhgIZIc2j39NLIhpJpq", "tf": 1}], "223713": [{"id": "6KBYefIoo7KydImq1uUQlL", "tf": 1}], "223720": [{"id": "1ZSu2nD48t0pnj0LcpdXGt", "tf": 1}, {"id": "5UbJK7IHuc6BSZCwagzp3L", "tf": 1}], "223733": [{"id": "0hOA8SoraNo2ZP1amtVYnY", "tf": 1}, {"id": "3U7H63zKWLjOuFZJUmTowp", "tf": 1}], "223747": [{"id": "1Y13csEpu3TK5gQdzGLrd8", "tf": 1}, {"id": "2enPRFda84VE2wtI8c86Uf", "tf": 1}, {"id": "4DVQN1iS7BCgwy2typKIFx", "tf": 1}], "223760": [{"id": "2fuKdZhBAH6sU0dPPTalDr", "tf": 1}], "223773": [{"id": "47euMdzPz6bdj7EKPy369S", "tf": 1}], "223782": [{"id": "1UBCUQp3areFyJZjTwLz9g", "tf": 1}], "223800": [{"id": "35ng4paFFvY2YiacXUP6PW", "tf": 1}, {"id": "3zrYNl1aMdFrQkcOjKVr5u", "tf": 1}, {"id": "7K9kbDWgbJmfNnN9LSoXB4", "tf": 1}], "223827": [{"id": "2bD9x9kN4wYyVoyckeqlLk", "tf": 1}], "223840": [{"id": "0gmbgwZ8iqyMPmXefof8Yf", "tf": 1}, {"id": "0qcr5FMsEO85NAQjrlDRKo", "tf": 1}, {"id": "78Nx4qNwmATqqcs4biKW1T", "tf": 1}], "223846": [{"id": "1QRhkgyZLIR1aqNPvB76ne", "tf": 1}], "223847": [{"id": "1sYSP7gKa5kdKIfhANfori", "tf": 1}, {"id": "5A6BJLZArq1MPjsnmcuk5f", "tf": 1}], "223853": [{"id": "2GyA33q5rti5IxkMQemRDH", "tf": 1}], "223855": [{"id": "74hmG1k2ASLQHYdljwM2Oy", "tf": 1}], "223863": [{"id": "1SBj3BmNJ5SNCoC0VtlR9Z", "tf": 1}], "223867": [{"id": "2yBVeksU2EtrPJbTu4ZslK", "tf": 1}], "223880": [{"id": "1MSM3Fo2fvnwVqMcz8Jhjq", "tf": 1}, {"id": "5OwponLnwCAYnWql6cwBru", "tf": 1}], "223890": [{"id": "6uebosHeOwzQT3ZBtBCbtu", "tf": 1}, {"id": "7zyLObYw4QUKQDyZOb4J0Y", "tf": 1}], "223910": [{"id": "1gyaphIqlNbfhlQTUJ8iNr", "tf": 1}], "223913": [{"id": "3jBCTvWRsLVgzryMaPJKhw", "tf": 1}, {"id": "79edhUCJIHerzdr8Tgclw7", "tf": 1}], "223915": [{"id": "2cop62KNgi55QqIozb5bMf", "tf": 1}], "223920": [{"id": "1cN13ivH3D66m9DoW2Z7iU", "tf": 1}, {"id": "2Cc4xF0pwkk3G3VE1YofUu", "tf": 1}], "223921": [{"id": "4kfEy7h6bWBS5OaDpccTap", "tf": 1}], "223927": [{"id": "4KupOOlpiji7VTKLm6b8nA", "tf": 1}], "223933": [{"id": "5T7LRFc3HfK4AN0r14ZbkQ", "tf": 1}], "223947": [{"id": "6ACiYjq5Q7e6BlhZEHz7cd", "tf": 1}], "223948": [{"id": "4YtMhT2Ko6FRwQoWcswYss", "tf": 1}], "223960": [{"id": "01R0Xdwje645C6xFCnMRvm", "tf": 1}], "223973": [{"id": "6lrRIfQDcikJ5y5DtyZPuJ", "tf": 1}], "223eftuwzfebe6v2tnmrol": [{"id": "223EftuwZfEBE6v2TnMrOl", "tf": 1}], "223ptixzqcuxzqyatz5kyo": [{"id": "223pTIXzqcuxzQyAtz5kyo", "tf": 1}], "224": [{"id": "31LIXek4OCRgKJn4RWg5Yb", "tf": 1}], "224000": [{"id": "1MxhhFSot6l3CI4abdhPMG", "tf": 1}, {"id": "4DBKiDC6keXW8a4deVQ0Qs", "tf": 1}, {"id": "5rjPINVemhJJL3JUiXLeV1", "tf": 1}, {"id": "76wlJTsge6ujLwcvOwbiV5", "tf": 1}], "224001": [{"id": "3vWtNiug49addenxdTmDXf", "tf": 1}], "224002": [{"id": "4SWWe2OYC4mqf40Gc2RSdl", "tf": 1}], "224013": [{"id": "35zWpeXJ71mprm8V9GOHpV", "tf": 1}, {"id": "39j3ulhZAiudnvNp7dwgYl", "tf": 1}], "224027": [{"id": "1awcbkmzafwSmo0cgyMFio", "tf": 1}, {"id": "23DZLSxCK6kM8FF2RlzKDl", "tf": 1}], "224031": [{"id": "0ADG9OgdVTL7fgREP75BrZ", "tf": 1}], "224040": [{"id": "5dHpbFmZjWucrol0M7aNGU", "tf": 1}, {"id": "6z23ntQL96zhacGOqQO87c", "tf": 1}], "224061": [{"id": "1LjxmkW3xRQP2HzswhYyyc", "tf": 1}, {"id": "3sHuIjfAzluc6S9cXoqfqC", "tf": 1}], "224087": [{"id": "4I58RPHVzDldHfK3t5HiZA", "tf": 1}], "224107": [{"id": "1MANhf0nwr6gFwsRJMeDbr", "tf": 1}, {"id": "5ngSGTy4Tw8cIBCMeIgoc9", "tf": 1}], "224120": [{"id": "4Qt4z5raRM4riRPtU55uAs", "tf": 1}], "224133": [{"id": "0SibPl0V9rpSmaqx4mXzmV", "tf": 1}, {"id": "19HjHUjCfDrEYhVSIKG6nK", "tf": 1}, {"id": "4w2iAP3X4FkpPb5kjRdIDx", "tf": 1}, {"id": "5CPqOpKSk0QcJ3dGdaWcRB", "tf": 1}, {"id": "78Az0Z1vNJgqv9QSB0ULLV", "tf": 1}, {"id": "7lY8aoN3wUR3NY4nUwigPv", "tf": 1}], "224153": [{"id": "6OY9OH03Wqro8K4mhri7QH", "tf": 1}], "224160": [{"id": "0fFotmAiRwLfpogfYs48PQ", "tf": 1}, {"id": "5SwCwWPx2LjBEkC8DXei4Q", "tf": 1}], "224170": [{"id": "5UjhWsB5rddZEPlNUcGDLV", "tf": 1}], "224173": [{"id": "4caYbCanhI1iKxVsLETOh1", "tf": 1}], "224187": [{"id": "12wSL3tGk3MtbDEhfG7xy3", "tf": 1}], "224200": [{"id": "3q1dhgO6MmeA7LUoz86BPh", "tf": 1}, {"id": "3uVmR6oQq0NluVZXkipKHV", "tf": 1}, {"id": "4EmdSvY5pvzu9COEtPOiR0", "tf": 1}, {"id": "6x3kWTpIhi8Rrte9BrYWJ5", "tf": 1}, {"id": "7cUXKXdigEIP8FgWbmckde", "tf": 1}], "224207": [{"id": "0iRk0TRxGqhQT9FTTGDQlb", "tf": 1}], "224213": [{"id": "25OE5Bx7Vjo3aVmQjJWXGG", "tf": 1}], "224224": [{"id": "09CWfcYFhVhB1Bzfz1cLJ7", "tf": 1}], "224227": [{"id": "77j9HOrxUpWcjwra9jgvio", "tf": 1}], "224240": [{"id": "2Zuv8yMOYeF2TFERAOWJgS", "tf": 1}], "224246": [{"id": "53rhwRKKrsWaT6tuSzymdY", "tf": 1}], "224253": [{"id": "2ajhenDRiiAnCHHjsIOHhJ", "tf": 1}, {"id": "6EaLyLT4d2bvzX2XYYztQb", "tf": 1}], "224258": [{"id": "2S5LNtRVRPbXk01yRQ14sZ", "tf": 1}], "224272": [{"id": "5jJnlACnwFvyqNXmUZu8Nd", "tf": 1}, {"id": "7gZQfdEQpmwAoPHSbEHzms", "tf": 1}], "224280": [{"id": "2ZLkHOVY7dqXIyhN4YQ4FH", "tf": 1}], "224282": [{"id": "0Dw7uVJBAKCm6dfCoabJV9", "tf": 1}], "224293": [{"id": "3Nbcx1svCSzmyYG2I81YCZ", "tf": 1}], "224299": [{"id": "37n8qUcQJJYRJKNMILiVvR", "tf": 1}], "224308": [{"id": "0hAxyVU6Nro3equjEQdFq2", "tf": 1}], "224320": [{"id": "0Rj2yNpEvXOl8yn9UOuIRs", "tf": 1}], "224333": [{"id": "18vVJsD68uh386vlZWwO3d", "tf": 1}, {"id": "3f8TbkkP0VIdOKvLTMMTvU", "tf": 1}, {"id": "4gv9eyEf7cXViNTBXS2g5C", "tf": 1}, {"id": "5lN1EH25gdiqT1SFALMAq1", "tf": 1}, {"id": "5odFKr8lDYmdSyA1K4XDJF", "tf": 1}], "224343": [{"id": "2tVUhD4EtfOKb4n73BrIaq", "tf": 1}], "224347": [{"id": "14w4u5B03GZxJGwNWgnFRp", "tf": 1}], "224360": [{"id": "0Dw3M1B14FRabDfVYr5pEX", "tf": 1}, {"id": "3O0e0LHTpza0rYVDbZfQ4r", "tf": 1}], "224372": [{"id": "0PzZvi3PwXMuNlhaokdxfg", "tf": 1}], "224373": [{"id": "4Oi5LdwWqDUCwTTjNXnnyL", "tf": 1}], "224392": [{"id": "014J7jX1wSv0manSdRnveo", "tf": 1}], "224400": [{"id": "6I9Yt26av1rRl5UMHkMj62", "tf": 1}], "224402": [{"id": "0tBRo4P60DgKmg4jt48upm", "tf": 1}], "224418": [{"id": "27qSobohScQ8WnEzp02Tm4", "tf": 1}], "224427": [{"id": "41bIQPBE1lFN0mmw6Lmssz", "tf": 1}], "224440": [{"id": "4dEZbrokJ8lgNyrdL9ZTe8", "tf": 1}], "224453": [{"id": "5C25hyezPUXfOktnlSBAQ0", "tf": 1}], "224459": [{"id": "3jl1I9gvCXo5V9hu4hYGLY", "tf": 1}], "224467": [{"id": "1VHszDbet9D1SfmPKkWyqw", "tf": 1}], "224480": [{"id": "2V2s9scwJqfpBPnXNdCSdo", "tf": 1}], "224482": [{"id": "0To77mmBsRqtWIZHcnpMvT", "tf": 1}, {"id": "7nGVsZvWnSvQJGkuxTnOrS", "tf": 1}], "224487": [{"id": "2Vhd5uZB4brKHmM0MNxkZo", "tf": 1}, {"id": "6DsFZITJMPnh8z5XewfVmL", "tf": 1}], "224493": [{"id": "1zOaxkbS1kAY1gIi0g8sOm", "tf": 1}], "224507": [{"id": "7b71WsDLb8gG0cSyDTFAEW", "tf": 1}], "224512": [{"id": "5VQpJ2AY2iMzrRZKgcvNjh", "tf": 1}], "224520": [{"id": "0KOMzOpAeg3CNrs7UceEpO", "tf": 1}, {"id": "5cY6lJ8aUzXgzJIDOhKhlw", "tf": 1}, {"id": "65n4DkUhKUO4tECIabKwy1", "tf": 1}], "224533": [{"id": "0fsj3HxzBHev6EJ7OLFE3r", "tf": 1}, {"id": "0gDh8XfKdq9of5fxuyayq2", "tf": 1}, {"id": "7N1Vjtzr1lmmCW9iasQ8YO", "tf": 1}], "224560": [{"id": "7qveFKh99XSlkED6hTPAoX", "tf": 1}], "224573": [{"id": "41Fflg7qHiVOD6dEPvsCzO", "tf": 1}], "224586": [{"id": "1hCTxutVVYvggAQcUUUZAT", "tf": 1}], "224597": [{"id": "1RcABeMCAH0UQi0yF4drXj", "tf": 1}, {"id": "4LFBVDJV0xpayUvquQVzhS", "tf": 1}], "224600": [{"id": "2ZNdWbMx7cWPM1WWtcWyJ4", "tf": 1}], "224613": [{"id": "4ewmSyDLQ8Bl3Y6nRQsL7Q", "tf": 1}, {"id": "75FDPwaULRdYDn4StFN2rT", "tf": 1}], "224627": [{"id": "1XsIY6Pnj0xRZ84dHCXZfP", "tf": 1}, {"id": "3iyZRwIGmyXvdZMoxOlur7", "tf": 1}], "224634": [{"id": "7MHMTBev70bl00AlZfMMgR", "tf": 1}], "224636": [{"id": "2YnZA9UJFJoHM3BAUAmTHR", "tf": 1}], "224640": [{"id": "0Sgu2kKr8M0uuqKygi2wrH", "tf": 1}], "224653": [{"id": "0QKHlkLVjpaJF98RQiL9rR", "tf": 1}, {"id": "3bC1ahPIYt1btJzSSEyyrF", "tf": 1}, {"id": "3UW4SUehKFC6qmaTZ3OiTp", "tf": 1}], "224667": [{"id": "3gy6JIMU5Z7e9Yswdv49fG", "tf": 1}, {"id": "6njG8EYG1lrROn8P6q46eq", "tf": 1}, {"id": "6YoYLN155MLavQcl3bHmvY", "tf": 1}], "224679": [{"id": "1yZfyNarqiwD8eJBswXplK", "tf": 1}], "224680": [{"id": "77eJ2jPNaV8MiuQatgmeQ9", "tf": 1}], "224681": [{"id": "37eGbhE1xVFSvcKkqGb6i1", "tf": 1}], "224693": [{"id": "0kPeymTUiaidv48eRrMISu", "tf": 1}, {"id": "1NhPKVLsHhFUHIOZ32QnS2", "tf": 1}, {"id": "3pDhN3qB33AOPhQEkUCaWt", "tf": 1}, {"id": "5W3cjX2J3tjhG8zb6u0qHn", "tf": 1}], "224720": [{"id": "00f9VGHfQhAHMCQ2bSjg3D", "tf": 1}], "224733": [{"id": "72jsKj3VkYsGTIOgEUuG6Q", "tf": 1}], "224740": [{"id": "6Nl5jjykRxa7salssZ0aER", "tf": 1}], "224743": [{"id": "41WTP0gosjYD74B06uS2tL", "tf": 1}], "224760": [{"id": "15gVYensbJgM9QDIFjB01c", "tf": 1}, {"id": "7DEg5RLG8GOgt7NSrVAKKJ", "tf": 1}], "224762": [{"id": "58ctD8HaEUXJkdv7TTsmG8", "tf": 1}, {"id": "7a5OUYOGtWSHKlsZz4n3QL", "tf": 1}], "224773": [{"id": "1KeZgPUr54C8iz3FjqzVoz", "tf": 1}], "224800": [{"id": "6cCvSU7rUJtkaEZ19p0Mzu", "tf": 1}], "224813": [{"id": "378iszndTZAR4dH8kwsLC6", "tf": 1}, {"id": "6b3b7lILUJqXcp6w9wNQSm", "tf": 1}], "224827": [{"id": "2fM6IykCVPDUucdkbdX5mf", "tf": 1}, {"id": "5bycn7SuJzYnxte0W54mNX", "tf": 1}], "224836": [{"id": "3Yf8sVkFXThHDtkqtSNbpZ", "tf": 1}], "224840": [{"id": "0wmzw4EVXp2XrOC47r6IOK", "tf": 1}, {"id": "1wa0Tm0MFcIpSdzILgQnmm", "tf": 1}, {"id": "3s9f1LQ6607eDj9UYCzmgk", "tf": 1}, {"id": "41TcraLQnuKmJuJ13nNwSd", "tf": 1}, {"id": "6RtPijgfPKROxEzTHNRiDp", "tf": 1}], "224842": [{"id": "3pkbfqWxPWu0jLUbVayQaG", "tf": 1}], "224853": [{"id": "10M2Ex445zw585Ducldzkw", "tf": 1}], "224855": [{"id": "0ifIudDeWelhhKzNqP12jm", "tf": 1}], "224867": [{"id": "5IXV375WDokSNjZfR4GgnU", "tf": 1}], "224878": [{"id": "6ghGfGpipODLLDyzcolTGW", "tf": 1}], "224880": [{"id": "0bORa4VpL8NzyMXEI6UFGK", "tf": 1}], "224893": [{"id": "0qtK3XwbuG153dmwB8iepL", "tf": 1}, {"id": "7uQWtaM6QwPLVTnw2xEXhw", "tf": 1}], "224903": [{"id": "3edzl4zvKFi0D3iuF6cs2f", "tf": 1}], "224906": [{"id": "6UJA62VlS7ZaqLzFtu5wuI", "tf": 1}], "224907": [{"id": "1xShPgQbOUa98avWJQFDBY", "tf": 1}], "224914": [{"id": "4txpZk7WSjV1dsZAw5WYcT", "tf": 1}], "224916": [{"id": "0jBJIQuToUUOEx7JJkiPzm", "tf": 1}, {"id": "14X1WxiHXdVRJ99cMCBzOE", "tf": 1}], "224920": [{"id": "4esOae7i4rqTbAu9o5Pxco", "tf": 1}], "224933": [{"id": "1ULa3GfdMKs0MfRpm6xVlu", "tf": 1}, {"id": "40tnCfx2mTtHozyaRDcYC5", "tf": 1}], "224960": [{"id": "473dVAB97y06dfl6OBb1uj", "tf": 1}], "224973": [{"id": "6ASmDSPVQ5eAPyuqvkFJsA", "tf": 1}], "224987": [{"id": "63Nj3NsQkLQs2MKgWk1Di6", "tf": 1}], "224eqmt8cpnpv98j9l4imj": [{"id": "224EQMt8CpNPV98j9L4iMJ", "tf": 1}], "225": [{"id": "1rylJ0VXvhOzLGNm401iaI", "tf": 1}], "225000": [{"id": "0XdC2dBoSx4eWLI1EsZKSx", "tf": 1}, {"id": "1HzTvjlL2z1ok5QzfDvPrp", "tf": 1}, {"id": "1iLv1ieT9BZ3qsti9yTCnG", "tf": 1}, {"id": "2ASx7GNCypmXa7IiKILPwh", "tf": 1}, {"id": "3lJGbK6EnrCQ1MDKUSQ8Xt", "tf": 1}, {"id": "3McFoGzAMw63UDlS79C2RU", "tf": 1}, {"id": "4dA9hCQDGz9eloCRNacWfO", "tf": 1}, {"id": "517cAnPxsaxfrkKHHY41wB", "tf": 1}, {"id": "7mFDv6NNIn7Iq5kzMmoTSG", "tf": 1}], "225013": [{"id": "3NgDulHteTVdF026IxY5bW", "tf": 1}], "225022": [{"id": "0uYmQ3X53P03KWj83u5I59", "tf": 1}], "225026": [{"id": "1mQaehT2IA8PAb6drI1RNB", "tf": 1}], "225027": [{"id": "3cjPSKlHrekNwiE1fZybZ5", "tf": 1}], "225034": [{"id": "5Nkb9ux4VIUED4tjG1Z3KS", "tf": 1}], "225037": [{"id": "5jlLBqK31dOqXECKn3jlMX", "tf": 1}], "225040": [{"id": "5zXmmhtXrhDbYnScaYpqZg", "tf": 1}, {"id": "72a9JWKqJ8SGo0OdyCS12P", "tf": 1}], "225053": [{"id": "2YlZnw2ikdb837oKMKjBkW", "tf": 1}], "225067": [{"id": "7xTMNK6vQFI6JUctix5Rye", "tf": 1}], "225072": [{"id": "6k6akHra06uOgcICJYp4fM", "tf": 1}], "225077": [{"id": "2S9UiaHpsdB2s3ZNzCObLQ", "tf": 1}], "225080": [{"id": "1vMKBHGQtISTkLva8uZgtn", "tf": 1}, {"id": "6T689Jvh5KrSXyaPtUWZtQ", "tf": 1}], "225093": [{"id": "557FZwD9Npq8DJyWLHf5nl", "tf": 1}], "225094": [{"id": "6LRRTTt97J9LnK1D3YcNGB", "tf": 1}], "225096": [{"id": "1VUGWjzlqudhTqvhc17miB", "tf": 1}], "225106": [{"id": "6l9HDwqU46DHCuNyvbmFdP", "tf": 1}], "225107": [{"id": "6I1JuzUGxTAD0kDY65fg1s", "tf": 1}, {"id": "6O1tLGD9D6TDW3Py6Gw4lX", "tf": 1}], "225117": [{"id": "4dSUq6XjY2Z7X3IdyR0Aig", "tf": 1}], "225133": [{"id": "0CZ8lquoTX2Dkg7Ak2inwA", "tf": 1}, {"id": "2imkodSyg1hOZwZuE2fJdU", "tf": 1}, {"id": "6dugx9WBSS8TDxbKqp9zmj", "tf": 1}], "225135": [{"id": "67dyMPOUsbZ9Yg06PnfAAh", "tf": 1}], "225147": [{"id": "1z9kQ14XBSN0r2v6fx4IdG", "tf": 1}, {"id": "6O20JhBJPePEkBdrB5sqRx", "tf": 1}, {"id": "7Kt59L2ZZGtOnIhvMwzG6f", "tf": 1}], "225158": [{"id": "0tBePnYDUyacbXvTIvTGAi", "tf": 1}], "225160": [{"id": "1tq4UL9BB7BHuT6eorlX3X", "tf": 1}, {"id": "2lPACBENza3HRYBvQPOdWT", "tf": 1}], "225173": [{"id": "4s0o8TJHfX9LLHa0umnOzT", "tf": 1}, {"id": "5GWV1AwlBbiwbMu6KdUnr0", "tf": 1}], "225187": [{"id": "3zagi2b65in52cZnFSnyAG", "tf": 1}], "225200": [{"id": "3afeZ81GDy59tATovKyH6Z", "tf": 1}, {"id": "4Z1t1aMRif8ES212kTN8H2", "tf": 1}, {"id": "6YziRRY7UY6rZDim35Dolo", "tf": 1}], "225202": [{"id": "7kxYYjOYRO8HamP4RKBhJ0", "tf": 1}], "225205": [{"id": "0qy5D3OJre7SPJNMOL9I71", "tf": 1}, {"id": "4a87wpeqAcOv03pYihEzku", "tf": 1}], "225218": [{"id": "3qRHCvn70YpVFFkx3lrAYf", "tf": 1}], "225220": [{"id": "0LMdYkvJ4gcNr3d0D5dnt1", "tf": 1}], "225227": [{"id": "0k6DnZMLoEUH8NGD5zh2SE", "tf": 1}, {"id": "4KEFi1juFd2f77HgFYka4e", "tf": 1}], "225231": [{"id": "1w6rw61wFJLFGoELmsrTi3", "tf": 1}, {"id": "2sM5KAvI1jQPcTJk9ov60k", "tf": 1}, {"id": "3gEaSrF7vC2FhfAARGeCoK", "tf": 1}], "225233": [{"id": "6sbOGldEofWsQlq1GjdHJK", "tf": 1}], "225245": [{"id": "44anLRFhwsFuwG5T7JvOWY", "tf": 1}], "225253": [{"id": "6aRlUgqcLgrxQE3RMngjN5", "tf": 1}], "225267": [{"id": "2xHEAdEalJ5YcP0ur8kF6L", "tf": 1}, {"id": "5hHdrN23SMuJkAsoyUcN24", "tf": 1}], "225273": [{"id": "5e7LO2aDWOUlYa5QUhGyhE", "tf": 1}], "225280": [{"id": "2WfaOiMkCvy7F5fcp2zZ8L", "tf": 1}], "225293": [{"id": "6Gv1bomFXOnIfpkMiMOcT9", "tf": 1}], "225306": [{"id": "3UP54oSRjnikM8mBHmCJhE", "tf": 1}], "225307": [{"id": "6nJPHXRpKYv2yqtalEjKy5", "tf": 1}, {"id": "6TwfdLbaxTKzQi3AgsZNzx", "tf": 1}], "225319": [{"id": "52nvjYpyVy1vPvNtqKTbvM", "tf": 1}, {"id": "5VSnk53xAO9BmquVUqGZbV", "tf": 1}], "225333": [{"id": "1DnbKcNE0sYLK4LOmhtTv9", "tf": 1}, {"id": "1qLeX26IEu3kPWxPfyBMGd", "tf": 1}, {"id": "3X3XuCPTC95ARm9SguWsIa", "tf": 1}, {"id": "4mpAm83XX1iS63l8wmkEC6", "tf": 1}, {"id": "5XyItd5rFfdtoJsWHxON5x", "tf": 1}, {"id": "6ibyC3znjMsol5XiAvmJxI", "tf": 1}, {"id": "6Zp0xvhkmV7OE1iKuvVclq", "tf": 1}], "225341": [{"id": "2uROM73VxtppgLSE2k27nf", "tf": 1}], "225347": [{"id": "1cWD3SRnt48gFWzqTC3pWM", "tf": 1}], "225360": [{"id": "2cooNqkhh52uvZJeHTHUm4", "tf": 1}], "225373": [{"id": "0nDoWlJuMZQ3XfA70L2Loy", "tf": 1}, {"id": "1hGy2eLcmC8eKx7qr1tOqx", "tf": 1}, {"id": "2455Sj0F7wa9vhjK5BXtn5", "tf": 1}, {"id": "24CXuh2WNpgeSYUOvz14jk", "tf": 1}], "225387": [{"id": "4XEXrp37kZXpQTB2r5vWbS", "tf": 1}, {"id": "6bMfEx9nIYsmFjiJl6P9NY", "tf": 1}], "225400": [{"id": "4BMk6XhlXJW7ZgIS8vSBZk", "tf": 1}], "225464": [{"id": "1Tb6uFyZgr9FYWDIBRCO0x", "tf": 1}], "225467": [{"id": "6uufS093628MRruPbXiW5g", "tf": 1}], "225484": [{"id": "4uX8Wh4wxpLne11BhoHs5x", "tf": 1}], "225493": [{"id": "2HzMIJjLgXGbfSWzQlrKtZ", "tf": 1}], "225505": [{"id": "7Bstjkh8Ymg4r7cGAXBbnR", "tf": 1}], "225520": [{"id": "0Oa9mHOnH14GZ4toWwkf4c", "tf": 1}], "225526": [{"id": "1Eck97uRMlprKOOJN9oO1E", "tf": 1}], "225532": [{"id": "1qRsC0QNSTXiTvHeeUlN5k", "tf": 1}, {"id": "6dQBC3QPuRvnzi6J9HDCJM", "tf": 1}], "225533": [{"id": "1fSWxeRWN393cHwMmGMayj", "tf": 1}, {"id": "1U2xFfjK1QUuicENnW0iwv", "tf": 1}], "225542": [{"id": "7q3NthaBqFI6s0WnAlnIvq", "tf": 1}], "225573": [{"id": "6Wgy62vZBMu9dkcSl7Ib78", "tf": 1}, {"id": "6YLJCOynR32U4YXtsvzTdC", "tf": 1}], "225600": [{"id": "0IEvbpIyDb26zwhnFGzuLb", "tf": 1}, {"id": "489dYzwI1HSwrjTHZ7Fm5o", "tf": 1}, {"id": "6GbWNeR3P9MTCmSyPVHgb1", "tf": 1}], "225613": [{"id": "65yj943cpxnMmgwe2YEZag", "tf": 1}], "225627": [{"id": "4alHo6RGd0D3OUbTPExTHN", "tf": 1}], "225643": [{"id": "58jiO8fZTyFM0EB7Nliu0T", "tf": 1}], "225667": [{"id": "5EdlwzcgIAYs2HGvOnczPN", "tf": 1}], "225682": [{"id": "5ZiGdWZvv9kaWw1UFcmDur", "tf": 1}], "225694": [{"id": "0bCPJsVGDxPYwQMDZMi4NW", "tf": 1}], "225698": [{"id": "0OuWBW2Q299zvZCdLUPlLx", "tf": 1}, {"id": "4wIlE0wVdqBi1tFGuSAx03", "tf": 1}], "2256qkbsqdt53t5dz4kdcs": [{"id": "3BZGi1yUqQyCNC868AqUGG", "tf": 1}, {"id": "3GR5Qd34nif6bskCrhTZue", "tf": 1}], "225707": [{"id": "4DnEyHNO8MdhFYFrDq73BV", "tf": 1}], "225720": [{"id": "0taheMDGubABEnocamFyT5", "tf": 1}], "225722": [{"id": "1WUfx6nUmCSQqdvsi33Osm", "tf": 1}], "225735": [{"id": "3JI2mIJto0JuYbrq87aFqu", "tf": 1}], "225742": [{"id": "7thOGpKaWpPotq2U37UItx", "tf": 1}], "225760": [{"id": "5LiW25vFN2BzrceU27R8qy", "tf": 1}, {"id": "61veBHF4sj0pKNpXeHF1ah", "tf": 1}], "225773": [{"id": "0b9oOr2ZgvyQu88wzixux9", "tf": 1}], "225787": [{"id": "5Msytfzyrxcaj5mjs3M19e", "tf": 1}], "225800": [{"id": "1GoTvQP3JEeA8oh5I9b2xc", "tf": 1}], "225811": [{"id": "7DtaoVCnStRPqC1bs3xZ1Y", "tf": 1}], "225813": [{"id": "3FWPoYBDserKdzcattMFGa", "tf": 1}], "225827": [{"id": "1mkiNF3VroP3biGnvK0k0w", "tf": 1}], "225839": [{"id": "5QSYWruQQ7kBCHScI4xJ9g", "tf": 1}], "225840": [{"id": "2QuvT46pnd93GDBYCpSlBf", "tf": 1}, {"id": "3Gwq0zKnMWluOEPKh93BeC", "tf": 1}], "225849": [{"id": "4Hep6vGkBN5w9BL46omYBs", "tf": 1}], "225850": [{"id": "6Alp0TKptNKc1vkdr8LvVJ", "tf": 1}, {"id": "7LJkGyL4vVrtn1mho7BmtA", "tf": 1}], "225853": [{"id": "291jfQK5C4tNrLUJyMARNl", "tf": 1}, {"id": "7hVhRCDV100Jq26NGR7adw", "tf": 1}], "225855": [{"id": "0viNo3zi6rOaYr7wZwhH2a", "tf": 1}], "225857": [{"id": "6ZkeEVV8OVRuhZfzB28DlD", "tf": 1}], "225866": [{"id": "0PZRlp2wrQDausamlangtw", "tf": 1}], "225867": [{"id": "2MPxWQdCMjdZheBI4ytaW6", "tf": 1}, {"id": "4ui7r4nqNUl4HmTiO00CVC", "tf": 1}], "225877": [{"id": "0D8n26VxzYSDIMhDO5JPjO", "tf": 1}], "225882": [{"id": "4RADreHMvMkZwsPgPr9z5c", "tf": 1}, {"id": "6WhzFzROw3aq3rPWjgYlxr", "tf": 1}], "225916": [{"id": "1tS3YIyOAczsBzjub9PrZj", "tf": 1}], "225920": [{"id": "3xRcQ04b0l5RiU2w7lJhCD", "tf": 1}], "225933": [{"id": "1Ej96GIBCTvgH7tNX1r3qr", "tf": 1}, {"id": "1JIgaRnqtzS7DuGM3hVZU9", "tf": 1}, {"id": "1SyR0qHmGNRZQ49Z0rFU4A", "tf": 1}, {"id": "4ADL2wPwh8HwoWT6M9fjsz", "tf": 1}], "225947": [{"id": "6iajHa34cSiD5s42Cq9miJ", "tf": 1}], "225973": [{"id": "2UXfcIiYWyIvKBlHyNQlsD", "tf": 1}, {"id": "5dd8tOJwLqEvasVqvvrJzV", "tf": 1}, {"id": "5n0CTysih20NYdT2S0Wpe8", "tf": 1}, {"id": "7zSDDsIlks515d0tZGM64x", "tf": 1}], "225982": [{"id": "7GMszPpwzW9Yehj9Ox2QLD", "tf": 1}], "225983": [{"id": "6b8Be6ljOzmkOmFslEb23P", "tf": 1}], "225987": [{"id": "7lOzUJzsELALh5FQsPKTEn", "tf": 1}], "225xvv8r1ykmherswivnow": [{"id": "225xvV8r1yKMHErSWivnow", "tf": 1}], "226000": [{"id": "2HTfaqz4LcCHLWmyrEm4mZ", "tf": 1}, {"id": "46hy7Fomx8gRXze61Znil7", "tf": 1}, {"id": "4h6omEIukDMaWJpM70XEHG", "tf": 1}, {"id": "6sMmjtWC8NbGokD3kg24Z3", "tf": 1}, {"id": "7hdApflRI6aGuwfabUZCu6", "tf": 1}], "226006": [{"id": "7zTTDkkLkJ2iHAqq1daDCr", "tf": 1}], "226027": [{"id": "1AsRjeavWPH8sCQbjMP8Xh", "tf": 1}], "226038": [{"id": "57ciWTOKgrXVBxktMJyUB1", "tf": 1}], "226049": [{"id": "3u0n1VYwUNQyqiQTzJwwlL", "tf": 1}], "226067": [{"id": "2A6yzRGMgSQCUapR2ptm6A", "tf": 1}], "226080": [{"id": "6Pa2clpHusIUFEjtICP9eC", "tf": 1}], "226093": [{"id": "1KyA5lXW7cAgMLwxRdVAu3", "tf": 1}], "226101": [{"id": "2fxJDRmUMatqyZ6ZOQi7RD", "tf": 1}], "226116": [{"id": "3E895HtTn6lB40SA0l9EkL", "tf": 1}], "226118": [{"id": "22ps3KimZMRByWUdG6bLO8", "tf": 1}], "226120": [{"id": "3N03MS9KHbonPzDQAZ5kfM", "tf": 1}, {"id": "4OXjsRE0RQsOAalWabZRY8", "tf": 1}], "226133": [{"id": "0tNuJpBgtE65diL6Q8Q7fI", "tf": 1}, {"id": "2EeDqZf3Kh8i7wkPgDprkG", "tf": 1}, {"id": "3a6YKw9xPXgqzwtOKnsPCQ", "tf": 1}, {"id": "4s9daMgGFI0uvCIygEnkU8", "tf": 1}], "226160": [{"id": "1pKeFVVUOPjFsOABub0OaV", "tf": 1}, {"id": "1wLhwzPAtze5JT8qqXlqaO", "tf": 1}], "226162": [{"id": "5e45GhSF18JYoLpaq2F48h", "tf": 1}], "226173": [{"id": "2SLKMhxrgJZ8TEPwhCt1gh", "tf": 1}, {"id": "4yZB0cywBNhhpNe9fnqgjz", "tf": 1}], "226187": [{"id": "1zlclNkERGFrCxznXOgkD3", "tf": 1}, {"id": "7snrmC4Lz2skHvzYWKxKJF", "tf": 1}], "226200": [{"id": "7BuHdm4lQqcyG3qTwdkxus", "tf": 1}], "226227": [{"id": "46gS5nW8S0kDU4Uw6YatNt", "tf": 1}, {"id": "6N3xqtn7l3XK2F6Mwk0qp2", "tf": 1}], "226240": [{"id": "62LJFaYihsdVrrkgUOJC05", "tf": 1}], "226280": [{"id": "4k9pqSKBHYdTGjzNeRyQ0o", "tf": 1}], "226308": [{"id": "6lhBJwyNBMPr6ejjscUDCj", "tf": 1}], "226316": [{"id": "3VHNuIXr0uRzVFsw6kNFPW", "tf": 1}], "226320": [{"id": "7ieV1TBSMyf5sFiPh9X2ai", "tf": 1}], "226321": [{"id": "314ZkcV7oLWG8yWE7LABvH", "tf": 1}], "226329": [{"id": "5inW8wv4Ap9j8ji9gq046e", "tf": 1}], "226333": [{"id": "0sxEHZ8WEPPTWGFXYBdB3O", "tf": 1}, {"id": "1yeHVJsVPN3ZskQ398be1E", "tf": 1}, {"id": "4hq0S6wznq7SHDyMOFXL9i", "tf": 1}, {"id": "6pPNepnzBAMdPcE3vgyT3y", "tf": 1}, {"id": "79yRAE9yyOqVEyJ74heFxl", "tf": 1}], "226335": [{"id": "2k7GyFSbErjCvk1QlTChxL", "tf": 1}], "226349": [{"id": "4Htt3QaBWdLggq88rJI5MU", "tf": 1}], "226362": [{"id": "2q6ak3C7lXdsXj50FlPWNq", "tf": 1}, {"id": "7cSkOU3iJxyKqcmDIueU7U", "tf": 1}], "226373": [{"id": "1JkhKUXAoNivi87ipmV3rp", "tf": 1}], "226400": [{"id": "20ZAJdsKB5IGbGj4ilRt2o", "tf": 1}], "226413": [{"id": "3toP91RkMRQw7M0bScJ4F9", "tf": 1}, {"id": "6Ges5C2IE738iJh4HyQizQ", "tf": 1}], "226427": [{"id": "0z9PMxrUVfCLc3e7itESJL", "tf": 1}, {"id": "2QN3pPQYoKsh5dIgEVnsYG", "tf": 1}], "226440": [{"id": "41X9To0bQ4fpoSRri4NHiI", "tf": 1}], "226441": [{"id": "0mMmhuNtbJalQCZy5VhVwk", "tf": 1}], "226453": [{"id": "0fxU0Wr9laBGaNsrwJ07Pz", "tf": 1}], "226480": [{"id": "14geRrYSRz73sBbtPD4iPQ", "tf": 1}], "226500": [{"id": "4zFDDTSInTkLg0d0KzxqJj", "tf": 1}], "226520": [{"id": "5u5MvmVtitax9R1Mxh3reC", "tf": 1}, {"id": "7uE5g6xnf80YRfavpReowD", "tf": 1}, {"id": "7uTx2o4PJ7UC0oNjtGkaS6", "tf": 1}], "226533": [{"id": "2kWB9IV8EHDOU9EjgxWFrF", "tf": 1}], "226547": [{"id": "76dZuMVXjIyLPRLv00skGd", "tf": 1}], "226558": [{"id": "6OsEQa0fSWbsqbrF0aQip4", "tf": 1}], "226560": [{"id": "19u5G7pWq3Nj6lQiP4W4Hp", "tf": 1}, {"id": "62NQ8JoW3yfJ2WSmlnaogw", "tf": 1}], "226581": [{"id": "0fgZUSa7D7aVvv3GfO0A1n", "tf": 1}, {"id": "6p5abLu89ZSSpRQnbK9Wqs", "tf": 1}], "226587": [{"id": "7p72uUp9qIlFP1IRbAvcox", "tf": 1}], "226600": [{"id": "6Z4rmc0uujCpl8yXe3yjgI", "tf": 1}], "226609": [{"id": "55dTpNSiKqfv2WyVsn4YFF", "tf": 1}], "226610": [{"id": "6iCJCZqDJjmBxt07Oid6FI", "tf": 1}], "226613": [{"id": "4OCvd4ila7Zp0tEsFWs2hP", "tf": 1}], "226640": [{"id": "4faFAhOflLzhfJECveRwva", "tf": 1}, {"id": "6pTDjJzSJaciuxfx9lW8hg", "tf": 1}], "226667": [{"id": "04Glred2wGdSNH11Qh4EDe", "tf": 1}, {"id": "5UHuuQGEgMbZrYnHjQG9ny", "tf": 1}, {"id": "68owi91PuuLlARM4BTvNHv", "tf": 1}], "226680": [{"id": "2nvC4i2aMo4CzRjRflysah", "tf": 1}], "226688": [{"id": "6Y9JFYyGCcD34RJ7gTMcQM", "tf": 1}], "226693": [{"id": "7zSAI7Ae6DPVepN8MksKVZ", "tf": 1}], "226711": [{"id": "407tDPFK5oB7hxSDl5Tg4O", "tf": 1}], "226720": [{"id": "0HVj61S4pQJdQhgZP61G65", "tf": 1}, {"id": "4cOVTA2GfYTHw99AJDQpHo", "tf": 1}], "226733": [{"id": "4BP0An7SXctTY4kF41JxIQ", "tf": 1}], "226739": [{"id": "00Ia46AgCNfnXjzgH8PIKH", "tf": 1}, {"id": "3vv9phIu6Y1vX3jcqaGz5Z", "tf": 1}], "226743": [{"id": "7IBSffWIu7P2MC7kMwy2FM", "tf": 1}], "226747": [{"id": "11cDEev79fPKi6uJCjUhu8", "tf": 1}], "226750": [{"id": "0qsQZDAZIGsbGmYEMfhTSC", "tf": 1}], "226760": [{"id": "3lqT89gv8p3PYwXtr3ODjv", "tf": 1}], "226763": [{"id": "40xcrghLmBuKzRFSZ6klGZ", "tf": 1}], "226773": [{"id": "0OGDredxd4n2ai4IJjfLNH", "tf": 1}, {"id": "2BYdSTQjd7e836KDacYjQt", "tf": 1}, {"id": "6xrov7bSdx0KxLdztHEstZ", "tf": 1}, {"id": "71Cid4UeolaHRzdbmMDAVb", "tf": 1}], "226795": [{"id": "3c0NlyfimtupjK3PlaQDLl", "tf": 1}], "226813": [{"id": "3wKLgtriaPGVW9A3AoRE9l", "tf": 1}, {"id": "4cw0I3t6oxDCmnI1XGL0A2", "tf": 1}], "226840": [{"id": "6j8JZ34YSJ3Yf7r2n2IPCX", "tf": 1}, {"id": "7JjlC99O9Gub3yKge26LyK", "tf": 1}], "226846": [{"id": "0yFvWTLs3iIwDbc91noXGT", "tf": 1}], "226849": [{"id": "7DHX1Ng0V186U2idfFfjGi", "tf": 1}], "226853": [{"id": "1sZOwk7oLpsVH6R65wyktS", "tf": 1}], "226859": [{"id": "1ZKmKenpeY1Yr94kADGpQF", "tf": 1}], "226867": [{"id": "54ZPmGE1uOG9IYoUBSRSp7", "tf": 1}, {"id": "5YHmAO5OSZqyvs0X9O3hEK", "tf": 1}, {"id": "6QLFNz62dpOgQTloWuUbNh", "tf": 1}], "226875": [{"id": "1wAIjMwxC3KjRqHpaMkFvC", "tf": 1}, {"id": "7nbVbGjifh0m2fhPYqcI1R", "tf": 1}], "226893": [{"id": "4qknM1pQz53QOyfDVTjcM9", "tf": 1}], "226902": [{"id": "2kg9AijbBp9HrXjlxByPT3", "tf": 1}], "226905": [{"id": "3dcpXrvJczwaALgcy8f8IN", "tf": 1}], "226906": [{"id": "0fIFjeeLJjIBliWUCsxyMF", "tf": 1}], "226907": [{"id": "2AVL6hxC2kgvGb3CFKiqWJ", "tf": 1}], "226909": [{"id": "3xy8karhdpkltgdwj9FGbQ", "tf": 1}], "226920": [{"id": "5n2dJROsTksXOXKwLIpEnx", "tf": 1}], "226947": [{"id": "0UU6IOw7aZcUIu0iW7EfVW", "tf": 1}, {"id": "7tUEDtHchueeUJTfEFEhii", "tf": 1}], "226952": [{"id": "1fWwxmWor6QbvBeLSV428F", "tf": 1}, {"id": "5g2cx0mZFmCNp4GexaifFl", "tf": 1}], "226963": [{"id": "1PVza5KmhSJhz12OewWciE", "tf": 1}], "226973": [{"id": "2gpEHrWOXBpeAIGORiBWw5", "tf": 1}, {"id": "3dQ71J2HPHXpPqJ0tQdDHR", "tf": 1}, {"id": "4UmehW6tTXGC7HsuIGujMR", "tf": 1}], "226979": [{"id": "3nUqzhvYQK4VEbioFZKFw0", "tf": 1}], "226981": [{"id": "0JITWDB1tVUH2VUXmVtYpL", "tf": 1}], "226983": [{"id": "0trjvNuATk3tEwIpXRr16m", "tf": 1}], "226987": [{"id": "4LOoPg7TavHtNmCTOfd9XQ", "tf": 1}], "226992": [{"id": "1NbRWGX7hybvzBU1Y5ysVa", "tf": 1}], "226993": [{"id": "1hf823Dtg12gHo3d2R6Ne8", "tf": 1}], "226ds4gxn0ih3wzv7dzvl4": [{"id": "17Z23wxx1J0nicqNfImgUE", "tf": 1}], "227000": [{"id": "3jVtllWS5CFFWLQng8sKsr", "tf": 1}, {"id": "4PslQxk22ZmgBrUHmDfy7n", "tf": 1}, {"id": "6U6UoE9LfZjeM6esvEdgCP", "tf": 1}], "227010": [{"id": "1gqv45EWm4hL4CRdVq0dmu", "tf": 1}], "227012": [{"id": "2wJJNgD6GrKoQ435VxTRv6", "tf": 1}], "227027": [{"id": "06EL94D0TA27Ik0Ke5usbj", "tf": 1}, {"id": "0FyBloIEdLS3f3SodFiju1", "tf": 1}, {"id": "0jBjuo9ikAfl2gvwqwyiA3", "tf": 1}], "227040": [{"id": "4py6PECWsrYuAAUk84XmVI", "tf": 1}], "227051": [{"id": "4dzGb1o0RHNzE3omFM6PE1", "tf": 1}], "227056": [{"id": "6XSKfR48lYGFOaaBWEMWOb", "tf": 1}], "227057": [{"id": "5EITjsahjBbV3FjLOPzsfz", "tf": 1}], "227067": [{"id": "1SssFw74DdHVjRa6ADggdD", "tf": 1}, {"id": "2gtEGntMPE9byfiTa2pRpr", "tf": 1}], "227068": [{"id": "3FpEXAupLwCHwzeUBxF99S", "tf": 1}], "227080": [{"id": "0EJlpO8Z5Vqy4phgcqU84V", "tf": 1}, {"id": "3n69hLUdIsSa1WlRmjMZlW", "tf": 1}, {"id": "6KM0MPPSPGjBlQgdwIeJLc", "tf": 1}, {"id": "7gARZ2i5u5DHC1b1n1fML5", "tf": 1}], "227087": [{"id": "2vtXB4ShP4eprgRW1IYpAp", "tf": 1}], "227088": [{"id": "6VpQdig9pdpTSIFItgkJV5", "tf": 1}], "227093": [{"id": "3gRwYAsiX4e50J43BkmZxI", "tf": 1}, {"id": "43qp6nkM5O7uXuuFnr7GpS", "tf": 1}], "227099": [{"id": "6gpLTvmHWj12Z03hFgixkH", "tf": 1}], "227107": [{"id": "10ASBwZsp7oUUDsJEYz3uS", "tf": 1}, {"id": "1jvT3CCQpyysWB1JcqZwSi", "tf": 1}, {"id": "1MHtFj66arQ3vD4ZNK1RYy", "tf": 1}, {"id": "7fkbO9RJWW0zQAtXBu5ixb", "tf": 1}], "227120": [{"id": "32B1GPGcPvCSF6hjlp2fzL", "tf": 1}, {"id": "6cujVaIoC0DpnAWDJfSMIo", "tf": 1}], "227133": [{"id": "7ngm7sCw2N2HmSDsanrSWW", "tf": 1}], "227143": [{"id": "3E5I51qj8g7aG5e7oIccpi", "tf": 1}], "227147": [{"id": "0eQjA54TJkwTHDJKG8OkRg", "tf": 1}, {"id": "1nbMkRhfldXcmCyB83x8lK", "tf": 1}], "227160": [{"id": "5IdPVawDl9lz84nPj832is", "tf": 1}], "227173": [{"id": "26fw0kxJC9jfo9iPt7R2Yp", "tf": 1}, {"id": "2fja4gHzPsIXiK4bMeU0hN", "tf": 1}, {"id": "7iEHCU1oYlqg3PloCa9uXW", "tf": 1}], "227195": [{"id": "74nBXnBEUBzCPfJxq1CG2i", "tf": 1}], "227200": [{"id": "4u9Y4Z9i9VaAbBK7rW1Rha", "tf": 1}], "227221": [{"id": "3iDPALl8BoUbuXZgy6EOWY", "tf": 1}], "227234": [{"id": "1cVlW9WQiGlFdWUXFdFZGh", "tf": 1}], "227267": [{"id": "4BqQrDNmfGfujQ4wPRb5tS", "tf": 1}, {"id": "57yI1u6t6cFXbjgjQcRHug", "tf": 1}, {"id": "7Ar4G7Ci11gpt6sfH9Cgz5", "tf": 1}, {"id": "7MmG8p0F9N3C4AXdK6o6Eb", "tf": 1}], "227275": [{"id": "0eeeyCAGnGZInPtpkdYiPa", "tf": 1}], "227280": [{"id": "2up69Rho7swRdP1MHqzX3n", "tf": 1}, {"id": "62zFEHfAYl5kdHYOivj4BC", "tf": 1}], "227281": [{"id": "3kkWD4jESZLL9eXrzJypGH", "tf": 1}], "227306": [{"id": "5bqwpjoSR0rvWWp7QZuXfi", "tf": 1}], "227307": [{"id": "5X9mQ7bV2wY5S9uIZsasbs", "tf": 1}], "227320": [{"id": "32fKHW6Eac4yBXn9WY7Aic", "tf": 1}, {"id": "6QRwT0bcuIsLGRCqMDJrVR", "tf": 1}], "227344": [{"id": "4zQhv8XkDaFnd8NdouX2Gd", "tf": 1}], "227360": [{"id": "2dRvMEW4EwySxRUtEamSfG", "tf": 1}, {"id": "6qTvF9L5uVSx4F1C5gTLjx", "tf": 1}], "227363": [{"id": "5nKEBGtC5ORYnZMeOacpxG", "tf": 1}], "227368": [{"id": "6kUohQ7py1XEcQAhUgf2Zz", "tf": 1}], "227370": [{"id": "4JlwKFHsi0UXCKhTRbPaNY", "tf": 1}], "227373": [{"id": "4v51rv7iRmKL2c0AgeAHDr", "tf": 1}, {"id": "6wJwkMo278iWVlWl1XQ4WA", "tf": 1}], "227387": [{"id": "6NPK12AruoBw2PPBQuku95", "tf": 1}, {"id": "6zMUIb4uce1CzpbjR3vMdN", "tf": 1}], "227400": [{"id": "4KuO26KOVzDiciB8Z9NHZX", "tf": 1}], "227413": [{"id": "0jSRZBsn3RqAhBDzAefHAD", "tf": 1}, {"id": "6MHOg9xiYC2gj8zcASaLUo", "tf": 1}], "227427": [{"id": "2RVCkAsopqqwKHCKKtHVYP", "tf": 1}], "227440": [{"id": "7xyYsOvq5Ec3P4fr6mM9fD", "tf": 1}], "227451": [{"id": "5dR7h8Rxj1ko6f9dmKQc77", "tf": 1}], "227453": [{"id": "3HoYNJMxEgTLKiMXjXeHjs", "tf": 1}], "227467": [{"id": "2FTj8pmH8Knv821458tZSq", "tf": 1}, {"id": "4Y1pFoYkE9aulSGRD39nqU", "tf": 1}], "227476": [{"id": "2zDj4WjbNDmrRL6Z4YjjCA", "tf": 1}], "227479": [{"id": "2iwptWnvaDXd7RIOsSu6DG", "tf": 1}], "227480": [{"id": "2bZMOs3RjmhhGca6MEzjyl", "tf": 1}, {"id": "4yVO0wOhXsZC1RuPgHP524", "tf": 1}, {"id": "7x5xYW5W42OGPAdHUyyguy", "tf": 1}], "227493": [{"id": "1lCfZOuD64LR9J1woSivou", "tf": 1}, {"id": "2dpy9FSzqKGLZfr0JJZJWl", "tf": 1}, {"id": "7t7HQLZMu0E9ljRCmnqkU6", "tf": 1}], "227510": [{"id": "3u6A33KtGqfk2JYm0YmiYu", "tf": 1}], "227520": [{"id": "3e4lLl0zCsOmiXjl9rBfNk", "tf": 1}], "227533": [{"id": "3rMsX63C0IZVnOT5LGYoTH", "tf": 1}], "227557": [{"id": "5HH6DEBpqxJ7Ushnd8DRBq", "tf": 1}], "227560": [{"id": "2NKRbRdRIcaGCXTq7xEpWV", "tf": 1}, {"id": "2ORxCzIYVvQYzAUv3iLFfx", "tf": 1}], "227576": [{"id": "13EqDaY8tAIrf0dmLdSPmU", "tf": 1}], "227600": [{"id": "1Bt6TZfF8FSqdiHPN0vy4u", "tf": 1}, {"id": "3PP7TRychfSQiAZgtq1Xjv", "tf": 1}, {"id": "4OIUiGAPgvkfMpR0MDaaTi", "tf": 1}, {"id": "5RTeMqtMcVCOukwgiNg11H", "tf": 1}], "227627": [{"id": "0wQwka6aD8i7gyhpGFNHLm", "tf": 1}, {"id": "1nmZ8yqKkfooOuYvtFctDp", "tf": 1}, {"id": "2ZBalNGwjqdKJd29O76wBV", "tf": 1}, {"id": "7KA66zSwthBv5X9bNQEeX1", "tf": 1}], "227631": [{"id": "0ltO5bci13M68sTnEctBxR", "tf": 1}], "227640": [{"id": "0uvBet3H0Q08SIAl90hIp1", "tf": 1}, {"id": "4yzXvKrnhzV39vbI9fT0ff", "tf": 1}], "227655": [{"id": "371H6HjS4SXGbQ9IVfFUIL", "tf": 1}], "227681": [{"id": "6dvhaeKxtP4rcDZ55fnqua", "tf": 1}], "227693": [{"id": "0TaT50ZZxT4ytZxuqkE3A9", "tf": 1}, {"id": "4WzhjxvLP95y7AMDy0Atwb", "tf": 1}], "227707": [{"id": "0sXvAOmXgjR2QUqLK1MltU", "tf": 1}, {"id": "2b4SSorCTQ2VzmllaeWuuT", "tf": 1}, {"id": "2X6okzhnNPSzh9yxDMHHe3", "tf": 1}], "227709": [{"id": "1LTR96tLqCxINVW2MkSEFf", "tf": 1}, {"id": "7uH20mELeQelsiMNCh78gD", "tf": 1}], "227726": [{"id": "72vPueDUvJcL3MCPb55RHR", "tf": 1}], "227727": [{"id": "24BSTATmWEmrPOgEM17bfN", "tf": 1}], "227736": [{"id": "6OpHDI8lRiqHLqmUIYUxVr", "tf": 1}], "227738": [{"id": "5m7nNrNPOwpxT15ksFIGSE", "tf": 1}], "227741": [{"id": "235LXPXfi0SmOaS9TaCh3c", "tf": 1}, {"id": "5jzKL4BDMClWqRguW5qZvh", "tf": 1}], "227747": [{"id": "2kYf8lZWXI4Ajd7ZhVhKhu", "tf": 1}, {"id": "5SOt2NdHbsUz3PyTG4sV1s", "tf": 1}], "227755": [{"id": "6DkmFhzJrkVhDlcgcEy7Pc", "tf": 1}], "227773": [{"id": "5HSMoHAy3sH6ByONlp0DIa", "tf": 1}, {"id": "5PCe0RKfhq7wB7vyQOIg9w", "tf": 1}], "227779": [{"id": "3CLd7BfvgsBwBUI8kwFLU6", "tf": 1}], "227787": [{"id": "4odiyU3myG29Ld0wurMfE8", "tf": 1}], "227800": [{"id": "3xCSmBYkXp6msX9z9MrFRc", "tf": 1}, {"id": "4hAhyE1iL07EIUJnqw2bsV", "tf": 1}, {"id": "6fybp4N6eW3bsFAvARxyVe", "tf": 1}], "227813": [{"id": "4rHmKlFRiFzabiVO6e9w2e", "tf": 1}], "227827": [{"id": "4u7hiFNXUeTG3A4dqQrkcd", "tf": 1}], "227833": [{"id": "3s4U7OHV7gnj42VV72eSZ6", "tf": 1}, {"id": "61dCUoMCg28qEBzrW6htYM", "tf": 1}], "227840": [{"id": "7eth0jUe6YneLljRNBeplO", "tf": 1}], "227853": [{"id": "33y08bwbpU8Fn8KzBm5lAy", "tf": 1}, {"id": "6RX5iL93VZ5fKmyvNXvF1r", "tf": 1}], "227867": [{"id": "15GJ5u94ls3eciXNh6YDER", "tf": 1}, {"id": "5a251qN4R86hro8UZGuO4E", "tf": 1}], "227872": [{"id": "5ajEdjV7VfH15GqSL8tSus", "tf": 1}], "227880": [{"id": "28jHD8xBLnN8esbroQ6zz8", "tf": 1}, {"id": "4lCv7b86sLynZbXhfScfm2", "tf": 1}], "227893": [{"id": "00QyLmjxaSEE8qIZQjBXBj", "tf": 1}, {"id": "0kUMtZVaYb7EETkBdrEXXA", "tf": 1}, {"id": "1mXuMM6zjPgjL4asbBsgnt", "tf": 1}, {"id": "1wTx8XqC5HnsppDY3sWWaE", "tf": 1}, {"id": "4Aa6cwl4QQMo61ej9Ucxeu", "tf": 1}, {"id": "4r6eNCsrZnQWJzzvFh4nlg", "tf": 1}], "227895": [{"id": "6jiDCykWPHvMlkYwMUFYvd", "tf": 1}], "227907": [{"id": "2gT8OWcAgPg0yawg1qw4Nv", "tf": 1}, {"id": "5L0KDoZklMgs9GPoonneEl", "tf": 1}], "227911": [{"id": "1jHCw2Ek5I4H8gshB7DJtN", "tf": 1}], "227920": [{"id": "3aA5fk4c6a7e5HM4rJqkSF", "tf": 1}], "227933": [{"id": "0weAUscowxeqDtpCgtbpgp", "tf": 1}, {"id": "5Sbf1ONFdUHbb88m9VUqDN", "tf": 1}], "227947": [{"id": "3uotsVdKcolpIxr0WHnaPe", "tf": 1}], "227960": [{"id": "2aIdVb8v9KTpEZnftkz2mD", "tf": 1}], "227973": [{"id": "73lcrkJKuPLoMWF0UnecCb", "tf": 1}], "227976": [{"id": "6xuJuA7F6ey3aULMRY4QWQ", "tf": 1}], "227984": [{"id": "4pEEaVhg7B1JJks7HmBNQI", "tf": 1}], "227987": [{"id": "190jyVPHYjAqEaOGmMzdyk", "tf": 1}], "227990": [{"id": "6xzQ1uSk2Rzz6Xdf8xBnWn", "tf": 1}], "228000": [{"id": "0hsMhZA3gguNuHOcDsGmOf", "tf": 1}, {"id": "1i7MnatuVb8zlDInTe30JP", "tf": 1}, {"id": "3xHC9yugYtjibz2908Mch5", "tf": 1}, {"id": "6SooMzpsDiPHFoLsk9XAvU", "tf": 1}, {"id": "79nopNMm3rJSUfQfMkG0Ur", "tf": 1}], "228010": [{"id": "5E9QTD8vk09mHUgpj8MCIt", "tf": 1}], "228013": [{"id": "4lDKORchTM8Rd0PFQFXTLX", "tf": 1}, {"id": "5VCk4tEn6pXqDqOGBNNmdt", "tf": 1}], "228040": [{"id": "03nYlT73VrrZdiw3ZaTuti", "tf": 1}], "228042": [{"id": "0lstGz2advSx5VqY8olvzt", "tf": 1}], "228053": [{"id": "0QfYrtWTIrvl282F8KlKis", "tf": 1}, {"id": "3ttzGcgmxvD8iGyb3NEZVr", "tf": 1}], "228067": [{"id": "1Z6lKdYhwp8WYoBqGCKxlM", "tf": 1}, {"id": "6zTABPrCYA8fm5ZpWrzKbz", "tf": 1}], "228070": [{"id": "2EKabowHBT6GRBK1mWJ5LT", "tf": 1}], "228080": [{"id": "7L4w1yQnlhqo4oUjpW53wz", "tf": 1}], "228092": [{"id": "3f04ysVYLQoaKFHLHjezws", "tf": 1}], "228093": [{"id": "1eq1wUnLVLg4pdEfx9kajC", "tf": 1}, {"id": "6IuFbYBWwzcJfOPRGrqjjH", "tf": 1}], "228112": [{"id": "3OTSBoYKO7HzGVj8Bu2OH9", "tf": 1}], "228120": [{"id": "0ZM89pj4zwJWpForACkpEY", "tf": 1}, {"id": "12LU5Tp6xEaJ8qMdaLO4MW", "tf": 1}], "228133": [{"id": "2Bs4jQEGMycglOfWPBqrVG", "tf": 1}, {"id": "2kt06ZsD735FYBZO8yAAQs", "tf": 1}], "228141": [{"id": "2GblQ918RbkOs4Yo1Rpkcj", "tf": 1}], "228147": [{"id": "1OJkKHmXsZVKtWlECdpDAe", "tf": 1}, {"id": "2xyi5jBkaQ741tXWTiqyr0", "tf": 1}, {"id": "2Z9B8sd6HgEfCWqvOfhFD0", "tf": 1}], "228148": [{"id": "6VpwX2LWXHFbblt00zPCCh", "tf": 1}], "228159": [{"id": "3tHAB8FI4rfULUHHG1d2Ct", "tf": 1}], "228160": [{"id": "2aKoElQmZWu2ZMCB3f2tbc", "tf": 1}, {"id": "3qIFYKztoCRa8I4a5J3BLF", "tf": 1}, {"id": "6VcyvtPgCTDJcay6h31cji", "tf": 1}], "228169": [{"id": "2M71Inc9camxaIGtmQ6I87", "tf": 1}], "228173": [{"id": "1CyCmgz0gm4AjvLE7JUYRm", "tf": 1}], "228187": [{"id": "1iQi4lFpgIPTMeGXlQqZKk", "tf": 1}, {"id": "1nUdWC6puxcV285AZfLokl", "tf": 1}], "228197": [{"id": "41rPWPCQotore8Ywk8lGOA", "tf": 1}], "228200": [{"id": "4aWmUDTfIPGksMNLV2rQP2", "tf": 1}, {"id": "5AgTL2WmiCvoObA8fpncKs", "tf": 1}, {"id": "7CUYHcu0RnbOnMz4RuN07w", "tf": 1}], "228207": [{"id": "6rrTr2HEAzlpC4KWZxF3S1", "tf": 1}], "228211": [{"id": "3VXnDxWmTQTxTVW0eCEZX7", "tf": 1}], "228240": [{"id": "04KTF78FFg8sOHC1BADqbY", "tf": 1}], "228250": [{"id": "6tgknDU0VMbXILuWixFKKn", "tf": 1}], "228253": [{"id": "0B2RttXEiyXsMeQ7mMP3EI", "tf": 1}, {"id": "3221dI8XPRA2COFaFlDI1o", "tf": 1}], "228277": [{"id": "3Qu4Myn9UbtAEnTmBGbHPa", "tf": 1}], "228293": [{"id": "1CkvWZme3pRgbzaxZnTl5X", "tf": 1}, {"id": "7wIQKJIOrQaTbzrZKeq6V0", "tf": 1}], "228300": [{"id": "5UJshy5HDHdNEVqlJwzsQB", "tf": 1}], "228307": [{"id": "2lACaIy7bocCyGwJXGtwLy", "tf": 1}, {"id": "413zm3wEjCThE6tMNPqe30", "tf": 1}], "228320": [{"id": "34w1ycoersTjtBsRQsKzgT", "tf": 1}], "228327": [{"id": "4gRA0i5sxx3jAhHaVjPnUN", "tf": 1}], "228333": [{"id": "0dCr3qIupWh36ilLjRHi4P", "tf": 1}, {"id": "2GrdCnHVMh0DrkmMzFMJaN", "tf": 1}, {"id": "6CK4xXnpKHJQA4YFoQ6Ads", "tf": 1}], "228341": [{"id": "64ndFagAiHD7qHiGWRyitC", "tf": 1}], "228347": [{"id": "3DamFFqW32WihKkTVlwTYQ", "tf": 1}], "228360": [{"id": "04aAxqtGp5pv12UXAg4pkq", "tf": 1}], "228361": [{"id": "2jfmh71b4cFtelf8KOJT60", "tf": 1}, {"id": "4tRLfSHpbjlIjV97RPWr9Y", "tf": 1}, {"id": "5wLsOFWBXXyoAgX7qQ6wbo", "tf": 1}, {"id": "5ZEM9j0jrFr5RdHEbl2MYV", "tf": 1}], "228367": [{"id": "3WRIaWsws011vHMd9uzPjG", "tf": 1}], "228373": [{"id": "1gm616Plq4ScqNi7TVkZ5N", "tf": 1}, {"id": "2uNre8fPMLoYIVj1P93qVE", "tf": 1}, {"id": "4MPTj8lMMvxLwT3EwuXFop", "tf": 1}, {"id": "6c6W25YoDGjTq3qSPOga5t", "tf": 1}], "228387": [{"id": "7hrnaeVvXFAkvQOmjHJglY", "tf": 1}], "228400": [{"id": "4B0tKXJguUl5YqW5wDcjNe", "tf": 1}], "228414": [{"id": "68pL3hokJXKJ1vJSaEhKr7", "tf": 1}], "228427": [{"id": "3dh2LlmeMqKJbzn2WUgt3d", "tf": 1}], "228431": [{"id": "5TRaIECBIfSkeqkKoG6psm", "tf": 1}], "228438": [{"id": "5f5r2N4Lp9WoULWPH9zp2W", "tf": 1}], "228443": [{"id": "5kcvBnt6DPX3AMEsCx1qDh", "tf": 1}], "228467": [{"id": "08XmoAjG6I2vbsONnFmDWg", "tf": 1}, {"id": "336ZYcU6poBWi3s8yzRcAD", "tf": 1}, {"id": "5J1c3M4EldCfNxXwrwt8mT", "tf": 1}, {"id": "6L3VWDPDTQkQFkqvmpAUMU", "tf": 1}, {"id": "79Jhw5xn4gGn6PZak275gg", "tf": 1}], "228480": [{"id": "5da9eEbSCnQ5fae1k3lLaE", "tf": 1}], "228502": [{"id": "6mPstbtzhyqKmwefY4eVWD", "tf": 1}], "228511": [{"id": "2rl644SDyLDBBKhUPSFucq", "tf": 1}], "228520": [{"id": "6OkhYhe15RBubuthLKW0VA", "tf": 1}], "228522": [{"id": "5a3MulSI25BDyBGg1Gsfpz", "tf": 1}], "228533": [{"id": "23IataC4bHhT7D6KHA5VOe", "tf": 1}, {"id": "5CWWOxTehNz94b4Xs0xFYV", "tf": 1}], "228552": [{"id": "3J7scZVfz4DtK4j3u6d8mY", "tf": 1}], "228571": [{"id": "6YKb5UMzDOtfCfbPvJZ8XT", "tf": 1}], "228587": [{"id": "5WFOkjPayogqjXEHVfnBpD", "tf": 1}], "228600": [{"id": "0KBMx9uErneRij9qMvIplC", "tf": 1}, {"id": "0kZMyLzcsahrZq5kWj8ARz", "tf": 1}], "228613": [{"id": "5UIR8dRPP1GtdxYHYPwKN5", "tf": 1}], "228626": [{"id": "2SWpDaorS0j7fXFj9AJtFG", "tf": 1}], "228640": [{"id": "16Ah4QqH4mgYVXqfC4mdSd", "tf": 1}, {"id": "3JXLO03HcIKzIB1xuDSDrR", "tf": 1}], "228653": [{"id": "732x2Fy6jbt7qC70Zg463q", "tf": 1}], "228654": [{"id": "7l3E7lcozEodtVsSTCkcaA", "tf": 1}], "228667": [{"id": "20s3FayrStM8GY0m4dRFsw", "tf": 1}, {"id": "2yrRiQtE34zp4EuL9DvrdZ", "tf": 1}, {"id": "5EcvzboYmDIfXo9gPplsSB", "tf": 1}], "228682": [{"id": "06Pvy98db25O7wlfFFFIRM", "tf": 1}], "228693": [{"id": "6SqTyTqxNHJDWO5aFMjWV1", "tf": 1}], "228707": [{"id": "2B8sc82PFB2493l9pdyWct", "tf": 1}, {"id": "3XVBdLihbNbxUwZosxcGuJ", "tf": 1}, {"id": "7rfiXyFb5M9BqdkvKvVEiB", "tf": 1}], "228720": [{"id": "12C6ufD5zOWsQGHQY7aXRM", "tf": 1}, {"id": "5FBIJ3i1CWaZLf1VTNIh7B", "tf": 1}, {"id": "62ovcuwlrPHfLxueBGokp1", "tf": 1}], "228728": [{"id": "5Z7L8FJk0aRrpxYyvoCFik", "tf": 1}], "228730": [{"id": "1xLqgaP1cHcZzQRM0ycRUE", "tf": 1}], "228733": [{"id": "5DvHwMndofUgkhrzRyBMoX", "tf": 1}, {"id": "5ib3EGG06XUnUf7hzDnheL", "tf": 1}], "228747": [{"id": "2TF5z78mdoObRtPW9GhNzV", "tf": 1}, {"id": "37clf85ZAJGszhC15NxskJ", "tf": 1}], "228750": [{"id": "43eEoYZerwCiHaZiMbE02d", "tf": 1}], "228754": [{"id": "5znFetnJFcs6NwKo67xlcK", "tf": 1}], "228759": [{"id": "6PMU1fJY4Gly94ZBrkOa89", "tf": 1}], "228760": [{"id": "0FZ4Dmg8jJJAPJnvBIzD9z", "tf": 1}, {"id": "3Yzcwfm3sEQaaa3ENFC18h", "tf": 1}, {"id": "5ZY8CsGBDp8AJ31fPx6qds", "tf": 1}], "228763": [{"id": "3F2We6fYbrFOsmPrJrFUE6", "tf": 1}], "228787": [{"id": "2XTmGOFMklOUffBmovTUjo", "tf": 1}], "228800": [{"id": "2MJrwP7dCWU3Eh3BKfum0O", "tf": 1}, {"id": "4yA2SM7XCLkSgkBUSoZb5S", "tf": 1}], "228813": [{"id": "2PyuytS9WHUXcqzR1lJYV0", "tf": 1}], "228827": [{"id": "23kyUPJdiHQwmAH4NfCGvf", "tf": 1}, {"id": "47FjToieQbxqNnuiRRQtym", "tf": 1}, {"id": "5CtI0qwDJkDQGwXD1H1cLb", "tf": 1}, {"id": "6rPO02ozF3bM7NnOV4h6s2", "tf": 1}], "228837": [{"id": "05dL7chWJaVjMJnGO1YCKk", "tf": 1}], "228840": [{"id": "0p1BcEcYVO3uk4KDf3gzkY", "tf": 1}, {"id": "4uvjOKsp7mSjrDhWdkLPBY", "tf": 1}], "228862": [{"id": "5EUPK2x1wJ5bERxjQ47lKv", "tf": 1}], "228867": [{"id": "0MrD47wtvAu6igsy8vqUzN", "tf": 1}, {"id": "39OPZvxdhToddt29z55Ukv", "tf": 1}, {"id": "3lVW4iUtV7XxZXAER3Z3Ry", "tf": 1}, {"id": "5wqB7S73zPUAtdcCvKZflz", "tf": 1}, {"id": "6iX9C7Cqgn0St5a6L25udL", "tf": 1}, {"id": "7q6BhGVElCaDYQqL3VhO5w", "tf": 1}, {"id": "7qm1JpihtROAIU1XpvqYHS", "tf": 1}], "228875": [{"id": "3TnhQSRwT3AVMdXw5JPq0x", "tf": 1}], "228879": [{"id": "4fwbGKNExPtPHbor1TBSY4", "tf": 1}, {"id": "5CZMYGXypciCWqiDKG5vgx", "tf": 1}], "228907": [{"id": "65N5mnAk0WOubXkCryAxEe", "tf": 1}], "228933": [{"id": "24PWKmemCvqfyVXODhoKHW", "tf": 1}], "228960": [{"id": "1npDfdIgKSiOwtDJJqgeBw", "tf": 1}, {"id": "2ig0x2zNvcOugS1Z0YCnHb", "tf": 1}, {"id": "4Svpc4QRvDW0J34AE30S9c", "tf": 1}], "228966": [{"id": "57nReJa69S1lEJGYHLCKlx", "tf": 1}], "228973": [{"id": "7x6ev0H9OAmvuDnyuItBZS", "tf": 1}], "228976": [{"id": "1oXHXIB8rHgwHSsPRNjEzn", "tf": 1}], "228980": [{"id": "5PwCuqzezD4a7mfxMNwk86", "tf": 1}], "228987": [{"id": "6h9xi8i9zVOXk5FqGqcBNH", "tf": 1}, {"id": "7kKLHjFif3r0HG5YyBTv6d", "tf": 1}], "228994": [{"id": "0nQLxiNGbbUoSGrxksETLm", "tf": 1}], "229024": [{"id": "7u5Q1iDGYPuqaqWhvxz20D", "tf": 1}], "229026": [{"id": "1Ioc85mqHwoQKvnI0p4dnW", "tf": 1}], "229027": [{"id": "4f49sFQko7jHLEFd3tCf5p", "tf": 1}, {"id": "7CJQUfl628ppAuH2MnTptQ", "tf": 1}, {"id": "7KSXAZLs1uv0qSA4GktduG", "tf": 1}], "229029": [{"id": "3u5bTqHMM1P34ZkbwzdckV", "tf": 1}], "229040": [{"id": "1m9yGw9LwTHc7s3i7ARXRn", "tf": 1}, {"id": "2ipxxnFmqMLWLcjpiIaKMc", "tf": 1}, {"id": "4BsX3Li27mT1QBN0eTRKEK", "tf": 1}], "229053": [{"id": "4XhrowM5IKGCRrY2HzYBH3", "tf": 1}], "229080": [{"id": "6ZANrVuAMp2rpjhfbOuJly", "tf": 1}], "229088": [{"id": "0BkvZes677Mcp5WVUQjRxD", "tf": 1}], "229093": [{"id": "2rbsEUWhJoC1fwTFihoOWI", "tf": 1}], "229107": [{"id": "5yGTQzYbEdY6B9RFZJypgt", "tf": 1}, {"id": "5ZyXUaBaeZYAZqHxKX8cKL", "tf": 1}, {"id": "69ghzc538EQSVon2Gm3wrr", "tf": 1}], "229133": [{"id": "5MA74oQBT1lVZtAVuMJAm0", "tf": 1}, {"id": "6oXaa9IjYnhaS0Fl9QzMp9", "tf": 1}], "229144": [{"id": "3NFvJh1TLTGnefNSNtydg2", "tf": 1}], "229147": [{"id": "0DbRkFE2KAyNXnKzD9inpV", "tf": 1}], "229149": [{"id": "6HUeSTt2RaKYIiJrnjzaCd", "tf": 1}], "229160": [{"id": "2de98HzQLgj4mN9X68IjAu", "tf": 1}, {"id": "6IVo7BWwGCLMaZfM7AH3iO", "tf": 1}], "229165": [{"id": "6KqWBiEZxRmPPGDc0PkRoV", "tf": 1}], "229167": [{"id": "5d8802FVRCxulddNtmjq2I", "tf": 1}], "229168": [{"id": "0tGmt2K3YvmCmvl4yV6InX", "tf": 1}], "229179": [{"id": "5xN3JHczV9RWdS7KYKOvAZ", "tf": 1}, {"id": "7mZPiASBnzei5lODsfLFLY", "tf": 1}], "229181": [{"id": "0sirCV8os5AwHHaMa3IDyX", "tf": 1}], "229187": [{"id": "3Gmt6Ki1tySCY6sXvmnR1Z", "tf": 1}, {"id": "7hbgCKddEQhCVXHsMdHebN", "tf": 1}], "229197": [{"id": "6NWD6siQErobvmydHcmhCw", "tf": 1}], "229200": [{"id": "75dBEvc6WfD8ZJpHV7CQSp", "tf": 1}], "229213": [{"id": "6K0Cw5dXlVy20zQFpA8vUm", "tf": 1}], "229219": [{"id": "3mbcpcRiAzeycvnX2YYLY0", "tf": 1}], "229227": [{"id": "1Hpe55FfvUHQF9rAT9iXB5", "tf": 1}, {"id": "4v23f4oo8oqlBfVMQgj8qa", "tf": 1}], "229238": [{"id": "2eGFixlUmSK3Yei80riTVe", "tf": 1}], "229240": [{"id": "2GJEMlKxt3GL2rJMOTET6Z", "tf": 1}, {"id": "36lkJSDyMEZoWTqtRj8Q8q", "tf": 1}], "229285": [{"id": "56khZQKfmdTikYbbZLgxAY", "tf": 1}], "229307": [{"id": "0arymh4a4YsUaps34DfA7L", "tf": 1}, {"id": "0gJO3qjzYbIhoHFRtArifw", "tf": 1}, {"id": "2VsIWeVLvZfWGpB1yOPXun", "tf": 1}], "229320": [{"id": "3mTEYjm3kIm4YzJ5zxJZjs", "tf": 1}, {"id": "4bm3nRCNGrFDINkMxEAGrf", "tf": 1}, {"id": "58MeeOMk6PMQxXWY9YCNPD", "tf": 1}, {"id": "6zeeWid2sgw4lap2jV61PZ", "tf": 1}], "229333": [{"id": "0DO5Qkdbtym514lDNy6LC2", "tf": 1}], "229347": [{"id": "03b1NUHnoavfpLLKcEMfIb", "tf": 1}, {"id": "4zEi4tr3lEhiAvTRxEzbEz", "tf": 1}], "229360": [{"id": "2bJvI42r8EF3wxjOuDav4r", "tf": 1}, {"id": "5D59kJUcYmJPLDcx0Co2ol", "tf": 1}, {"id": "6habFhsOp2NvshLv26DqMb", "tf": 1}], "229369": [{"id": "1n0VqMms2yoTGVvunXenQA", "tf": 1}], "229373": [{"id": "0UN5OvKlbg06LnZyVk48ll", "tf": 1}, {"id": "7x7kYJwduClF3I0ozJpNsZ", "tf": 1}], "229387": [{"id": "4Ft0391aLVNtCPPseh98lp", "tf": 1}], "229400": [{"id": "2XpjmHq0CygfO5FV5d5Hu6", "tf": 1}, {"id": "5bXLxmqFpKDPbbpkAa9m6V", "tf": 1}, {"id": "6Vc5wAMmXdKIAM7WUoEb7N", "tf": 1}], "229413": [{"id": "4T3fNx3CgwDRRYgmFCbD4J", "tf": 1}], "229426": [{"id": "1WsEgieHsWWndAzLkmV105", "tf": 1}], "229440": [{"id": "5GyvNF7yA07O0ZgGis2JVi", "tf": 1}], "229456": [{"id": "6it15CsDlkqB7N4lF0C1qM", "tf": 1}], "229467": [{"id": "0pwYLVXVknPSGUQb39cePC", "tf": 1}, {"id": "0tZ3mElWcr74OOhKEiNz1x", "tf": 1}, {"id": "13aKGvTil3UUw1yk0pA9fG", "tf": 1}], "229480": [{"id": "5PrHp3PRK78k18zrwgyxS9", "tf": 1}], "229493": [{"id": "2gJPWGnwUMEFoTDqEndLfR", "tf": 1}], "229507": [{"id": "5VBcEJ4mtXTmVEJtc7hx2g", "tf": 1}], "229510": [{"id": "0Gx4VrHzS7pZOEAGrmXXBH", "tf": 1}], "229520": [{"id": "1Jgaw4deeHcbldSmKbP5h3", "tf": 1}], "229526": [{"id": "2JzZzZUQj3Qff7wapcbKjc", "tf": 1}, {"id": "7wqSzGeodspE3V6RBD5W8L", "tf": 1}], "229531": [{"id": "3JyvSSU0VnlMUsQckyEVfX", "tf": 1}], "229547": [{"id": "3FuwVLUDf7QCwVaVmUB5F2", "tf": 1}], "229557": [{"id": "5UqivtkoiPTXrJu6GIt1mh", "tf": 1}], "229560": [{"id": "1AWjS2iHs8zNq21Niy3T50", "tf": 1}, {"id": "1M4Wy6jRce1x17qyE7yQAB", "tf": 1}, {"id": "5DsD9rUwGiiWZxyDPkm48V", "tf": 1}], "229565": [{"id": "71G8h9UiqlkXFvBUOKFviS", "tf": 1}], "229573": [{"id": "5OPgPWsCaeZDvHudPzVftQ", "tf": 1}, {"id": "7CZyCXKG6d5ALeq41sLzbw", "tf": 1}], "229587": [{"id": "1OFKUn2VLafrHj7ybnap0Q", "tf": 1}, {"id": "7fzNBlEWWRQIJrUZ1KaEwH", "tf": 1}], "229600": [{"id": "23mnIH4CZemgZgkyb0W1cC", "tf": 1}], "229606": [{"id": "2ex8jWyy3ewSdlytVPdjhk", "tf": 1}], "229627": [{"id": "3Vt6a0rOyb4nGM7rBzgK2C", "tf": 1}, {"id": "5tYv99LXO4gEXU8BfWT5yn", "tf": 1}, {"id": "7cG3wfohoNDSp2M8FWrgTg", "tf": 1}], "229640": [{"id": "1NurK1Rze21ZiVpXptNEeJ", "tf": 1}, {"id": "3FtYbEfBqAlGO46NUDQSAt", "tf": 1}, {"id": "4OGupqrF7u7wM4yLRMpL0p", "tf": 1}], "229645": [{"id": "7hY8tAAC9j8KFbStmpSamx", "tf": 1}], "229670": [{"id": "51rXHuKN8Loc4sUlKPODgH", "tf": 1}], "229680": [{"id": "7JVIiaJPFiZypYSOMREhhA", "tf": 1}], "229693": [{"id": "2M4pc3d5VTELAnjCkivkOf", "tf": 1}, {"id": "2UXEwIOtNGUUgGdXnds8V7", "tf": 1}], "229695": [{"id": "7IRQl8neWUlBT7UFcLg6n6", "tf": 1}], "229720": [{"id": "222B3aljXx6fFwKmFjuBED", "tf": 1}, {"id": "3HvJkF7TFCt1SN3QXODJad", "tf": 1}], "229733": [{"id": "2cCE88eift4HGqdCVYVn3t", "tf": 1}, {"id": "2e8r5YIPMCxXVJPPfwaSK8", "tf": 1}], "229747": [{"id": "6TaqooOXAEcijL6G1AWS2K", "tf": 1}], "229760": [{"id": "6LxcPUqx6noURdA5qc4BAT", "tf": 1}], "229773": [{"id": "1CAw3ethNuSDPf3E7luSFF", "tf": 1}, {"id": "4tOmFSoQA9ji8lTxAbbvq1", "tf": 1}, {"id": "5KawlOMHjWeUjQtnuRs22c", "tf": 1}, {"id": "6WaYiQUPel70HUaCZj5eND", "tf": 1}], "229800": [{"id": "1yeLSqz8u8ip9NnzjGs7lQ", "tf": 1}], "229805": [{"id": "1Oaq4rq7EBVUiXGh7yxuYL", "tf": 1}], "229813": [{"id": "1mRBJdpIgc3jZH8C3cN2WV", "tf": 1}, {"id": "5s7xgzXtmY4gMjeSlgisjy", "tf": 1}, {"id": "7cVmKBwzPsh4Fmb6SplfEm", "tf": 1}], "229827": [{"id": "1Umpo1hUyNgLkpNfPR5UTA", "tf": 1}, {"id": "28pCepAdwvCSfqdoVWDw67", "tf": 1}, {"id": "6IAOkZxfTzpRDL0nAAynjq", "tf": 1}], "229840": [{"id": "14EORgkbXqIx5K4Haucmnb", "tf": 1}], "229849": [{"id": "0qYTZCo5Bwh1nsUFGZP3zn", "tf": 1}], "229851": [{"id": "51hSi1p7g2KdXg7fJA1Hgp", "tf": 1}], "229853": [{"id": "3xIwnKhZxWxKcecqrfXBJj", "tf": 1}], "229862": [{"id": "2r4DozzHauSjM6NJ7szgVC", "tf": 1}], "229867": [{"id": "3rzYUfyzdZW96cHXnGn1xI", "tf": 1}, {"id": "7vNgFQlOb4cQMqBh67XkI5", "tf": 1}], "229880": [{"id": "6G9rDpbpGIf87oZyY9hS2O", "tf": 1}], "229893": [{"id": "3GbjOImkNo5nFT2GQxVr11", "tf": 1}], "229920": [{"id": "1pBFEy8cz0Fq4Pru0c4awd", "tf": 1}], "229933": [{"id": "0i8JFpqe9cKwnrcvoNgl1L", "tf": 1}], "229945": [{"id": "2bIIQIXgi5blVkSZ7Y2uTh", "tf": 1}], "229947": [{"id": "54FoR5osiOJtVae7SCdSnq", "tf": 1}, {"id": "5brMyscUnQg14hMriS91ks", "tf": 1}], "229952": [{"id": "52H18LsAjtvRnfYJDZhw2c", "tf": 1}], "229959": [{"id": "2pygzLN7fwCgeW5FNaugEm", "tf": 1}], "229960": [{"id": "0qgrrDnUUhyxpxbBznUnzg", "tf": 1}], "229966": [{"id": "28j9YpcO814u2WAv3RKstY", "tf": 1}], "229973": [{"id": "0TcOuAT1fL2RA1YUgTrBvK", "tf": 1}, {"id": "3XGBFBUEalGmIDcjvu4nrj", "tf": 1}], "229986": [{"id": "0IK8y0vAO0sM630HsxwLht", "tf": 1}, {"id": "74rluVXirwea83JzfkbjmQ", "tf": 1}], "229990": [{"id": "7gg0ogHVW2s7JKZoAOSGWB", "tf": 1}], "229mm2st7snw43nt8adlg8": [{"id": "229MM2St7SnW43nT8ADlG8", "tf": 1}], "22bdidvioswmmyehqxz7jw": [{"id": "0xOsIqxmLswEsKFGLwE5c5", "tf": 1}, {"id": "1WGUqMaTj8MN7QYZErtsVv", "tf": 1}], "22bf8gj8nozqztul4jcjuw": [{"id": "4eex3lCsrRlUgwue8C3R0O", "tf": 1}], "22bzoozkyz2jyyklpolnet": [{"id": "4OQjzsqsnSy4YPB9yaRh0f", "tf": 1}], "22c2wisjqrkgg1baaz12xh": [{"id": "27lm3yIbCVK72Sxzg2bC2q", "tf": 1}], "22cioflzb9z8he7wghyagh": [{"id": "22CIOfLZB9z8He7WgHYAgH", "tf": 1}], "22cvwuescyj2avf2wzoviq": [{"id": "22cVWuEscYJ2aVF2WzOvIQ", "tf": 1}], "22dhmfja31hkpc2lg0gvbv": [{"id": "22DHmfJa31hKpc2Lg0gVBV", "tf": 1}], "22dl6irgnynenkej7aw8po": [{"id": "5dewQ7ojISR32NAYNHFYWC", "tf": 1}], "22dvaydyxgxk1yxnzffmp9": [{"id": "1EyRK6kk3yW8ZmtqAPLZKJ", "tf": 1}], "22ebqdsukinydpq3a20h7z": [{"id": "22EbQdsUKInydpq3A20H7Z", "tf": 1}], "22f01qwlqdpxjpn8uqfz8n": [{"id": "22F01qwlQDpxjPN8UQFz8n", "tf": 1}], "22f5jwqnuh0qchqi2wqfs0": [{"id": "3hyi4CYvZ3K6EqAI2ja7pl", "tf": 1}], "22f5zyy1sxojjk6hzzfmc1": [{"id": "2EBCVPNAG46nbgs6jXPGvv", "tf": 1}], "22fragfscs4c7jccyczb4n": [{"id": "0DjnlLskmEjm5mbgo24WwD", "tf": 1}], "22fyyzydjtsffrgt9fofbi": [{"id": "0T3xmp3KqDklZ12Ze0Nm13", "tf": 1}, {"id": "5KNAsnZJ0g3hNvIJFvkHzI", "tf": 1}], "22gfneeyuxuely2qslemqx": [{"id": "22gFNeEYuXuElY2QsLeMqx", "tf": 1}], "22gnwshqclzkln0x8c69v5": [{"id": "2qgudkFpaRq2YcJDWhKW44", "tf": 1}], "22hktzkhksqqxtr54fsle6": [{"id": "2hRecZEvSXfGkSB40d4CaL", "tf": 1}], "22hxn36zdhnwwmkklv8l5e": [{"id": "27x2tIcwJswikH4dOgUg5x", "tf": 1}], "22itf02z2k23gpjumrmno3": [{"id": "2HYJoS3SWjIct4WS02DWtB", "tf": 1}], "22jdtyxdp8grcrlnsxjnx1": [{"id": "22JdTYxdp8gRcrLNSxJnX1", "tf": 1}], "22jnenesabg4vrcr1vow7f": [{"id": "22jnEneSABg4vRCR1vow7F", "tf": 1}], "22l7bfciakjo5xgsqgmiio": [{"id": "22L7bfCiAkJo5xGSQgmiIO", "tf": 1}], "22leqj7khtb2yvsq84fdqb": [{"id": "3QwBODjSEzelZyVjxPOHdq", "tf": 1}], "22lhzruf1d3lajbqkpwknv": [{"id": "1cx4RNSqEUedib8RqetJ0C", "tf": 1}], "22lvutztkquulgduoxpwzd": [{"id": "22lVuTzTKquulGDUoXpwZD", "tf": 1}], "22mek4iiqubgd9ctzxc69": [{"id": "22mek4IiqubGD9ctzxc69s", "tf": 1}], "22mgjjcdxcvkbuxqri81gs": [{"id": "1A5yplwEk6cJbAL63L6bkp", "tf": 1}], "22mhfcpbe5yzxwyekgjud": [{"id": "22mhfCPBE5YzXWYekGJUdS", "tf": 1}], "22mhvh6txsewwbwjmxl8it": [{"id": "3cen7DS8IWL3XADfzggKma", "tf": 1}], "22ml4er5kmsbukzplkffq": [{"id": "22ml4eR5KmSbUkzPlKffQE", "tf": 1}], "22mrovzmcn6wee4v6ua6dj": [{"id": "1j5cGcXWdHKTPQ2XgXODJI", "tf": 1}, {"id": "4hbGPfz03P8Nnh75mFIAoH", "tf": 1}], "22mthr01ezel6jmc5uwphc": [{"id": "7H8zey5My6uNdD2TxeCb9F", "tf": 1}], "22mvgb51prjnyckzgehnuv": [{"id": "1hsCcm0xujceILNvgRfrVB", "tf": 1}], "22nd": [{"id": "1aWV3uY3SIEZVbmv45oFWS", "tf": 2}, {"id": "2W0PgbJmayLcgbSyqGDqjq", "tf": 1}], "22nlm3iir9nlg0cuytmhmw": [{"id": "22NLm3IIR9NLG0cUYtmHMW", "tf": 1}], "22nq8jg98vsgghsybsijmo": [{"id": "22Nq8jG98vSGghSyBsIjMO", "tf": 1}], "22okyzlu46o7pf5kw4yfkf": [{"id": "22OkYzlU46O7PF5Kw4YfKF", "tf": 1}], "22otjomictqbue5tzacji": [{"id": "22OtjOmIcTQbUe5TzACJIs", "tf": 1}], "22ozybew53kgokp3gvvaqm": [{"id": "22oZYBEW53kgOKp3gVVaQm", "tf": 1}], "22p8crz9nwosgc9kr8yfpr": [{"id": "3rez7t0KrJuhx6HNAyFYWH", "tf": 1}], "22ps3kimzmrbywudg6blo8": [{"id": "22ps3KimZMRByWUdG6bLO8", "tf": 1}], "22qreigtzb9jayycjtmnw5": [{"id": "5TxRbuP3XjOIaV4DKapbsC", "tf": 1}], "22qrzijc0d35poqklocqau": [{"id": "7LdaPYlRo4pq6CBt44To2H", "tf": 1}], "22qy0arjhuzuuah9wrvzi0": [{"id": "22qY0aRjhuzUUaH9WrvZI0", "tf": 1}], "22rkxy3gxyzniju36nfueq": [{"id": "22RKxY3GXYzNiJu36nFueQ", "tf": 1}], "22rp3pnm3q2mtti0ogczpq": [{"id": "7crMiinWx373rNBZBaVske", "tf": 1}], "22s": [{"id": "0EYZTPdmYkj9Z2q95SepDx", "tf": 1}, {"id": "4yzXvKrnhzV39vbI9fT0ff", "tf": 1}, {"id": "6vye1WybNriUDdlZTbDidn", "tf": 2}], "22s0q6vlzmxsencm3cvhk": [{"id": "0vXVI7kPKK2p6XO4rybEHC", "tf": 1}], "22s5bo6h7jiojg2uw88l8": [{"id": "22S5BO6h7JIOjg2Uw88l8e", "tf": 1}], "22sesxzby1o1e19xjotayf": [{"id": "22sESxzbY1O1E19xjOTaYf", "tf": 1}], "22stmbjk27slwmtsdylt4u": [{"id": "22sTMbJk27SLWMtsdYLt4u", "tf": 1}], "22stsq5hrpbe4oiwgylpac": [{"id": "22sTSq5hrpBe4OiWgylpAC", "tf": 1}], "22sxyl6pujwivgwvggjlov": [{"id": "22SXyL6pUjwIvGWvgGjLov", "tf": 1}], "22t3rgajsn5qaud3gmaghx": [{"id": "22t3RGAjsN5qaUD3GmaGHx", "tf": 1}], "22tocwh0z9mcwoa1tfqbro": [{"id": "22TOCwH0z9Mcwoa1tfQbro", "tf": 1}], "22ucqavtwvvkokkj8f7oci": [{"id": "1FoMWISq2KNqKappkrG5Yo", "tf": 1}], "22ugd3brxzveunnhzp72a4": [{"id": "22UgD3bRXzveuNnhZP72a4", "tf": 1}], "22uzf19lxqw87kovkr79fq": [{"id": "22uzF19LxQW87kOVkR79Fq", "tf": 1}], "22vdizqfgxjea34mqxlt81": [{"id": "22VdIZQfgXJea34mQxlt81", "tf": 1}], "22vgedb5hykfatwluskfgd": [{"id": "22vgEDb5hykfaTwLuskFGD", "tf": 1}], "22vu1n5k6pouy6vonqo3oz": [{"id": "22vU1n5k6pOuY6VOnQo3oz", "tf": 1}], "22vuxjfeskekn6vx8tx5nw": [{"id": "1NNnmmBEaId0uoWfvtNd8F", "tf": 1}], "22wa3zp4mwtrxjklyahxjk": [{"id": "2q9ZHNJl6oCCci1DwAD45v", "tf": 1}, {"id": "7rNzap95cCcOafjFtofpBk", "tf": 1}], "22wcpwiq8euqcfof6wd0gg": [{"id": "22wcpWIq8EUqcFoF6wD0gg", "tf": 1}], "22wkqbmh8n7wzfso2vcljl": [{"id": "22wKQbMH8n7wZfso2VcLJL", "tf": 1}], "22wxe2yc9jzihicxylgaq7": [{"id": "22wxe2Yc9JzihICXYLGAQ7", "tf": 1}], "22x14": [{"id": "3yp9bZjCLb8E8Lqi01Sxz4", "tf": 1}], "22x1g0neicpmxueoxlguw5": [{"id": "3kGfazcbVvVkuZunzlLgTD", "tf": 1}], "22xkr7o6bzsa5bhiwrcpnk": [{"id": "02AT1Z0nscuElXMWBEzEKu", "tf": 1}, {"id": "1v0lDRJHo9mptTxoGFCQ7Y", "tf": 1}, {"id": "36lkJSDyMEZoWTqtRj8Q8q", "tf": 1}, {"id": "3FPiGFT19WRb4D0bZlw9PJ", "tf": 1}, {"id": "4N73fgEEennudER9hXnHOI", "tf": 1}, {"id": "4qg1esFGKNCCRYGVVNrIin", "tf": 1}, {"id": "5XI2EIihxzTlKLR4UUhedn", "tf": 1}, {"id": "65PbE3qfKElGTcweQMmbzf", "tf": 1}, {"id": "6lxOK8iqm78PEN2bXcjSEK", "tf": 1}, {"id": "7dQC53NiYOY9gKg3Qsu2Bs", "tf": 1}, {"id": "7rdtBpPpe4knfd7aD98h9X", "tf": 1}, {"id": "7xUVverKyPPPAW3sDqXhfi", "tf": 1}], "22xkrkw2heallxndqs14ig": [{"id": "22XKrkW2HeaLlxNDQs14iG", "tf": 1}], "22yq5tkmn8je7h1bq3pwh": [{"id": "22Yq5tkMN8JE7h1Bq3pWHS", "tf": 1}], "22z9qgudpmmqpbqmcv17it": [{"id": "3ZPaj6I2mWRq8pUZv1Peog", "tf": 1}], "22zpcx6nb9ppovklalvgec": [{"id": "4DmgUMnnCw27Tu5Jvqhm1n", "tf": 1}], "23": [{"id": "07fqonJcksfEG2Fav9SDA2", "tf": 1}, {"id": "0CFIH3diqmPfa6FRXEILLF", "tf": 1}, {"id": "0d2iYfpKoM0QCKvcLCkBao", "tf": 4}, {"id": "0efgEM1LQDbK43rqPH2Iyd", "tf": 1}, {"id": "0feKZeNQejawicLLYdyTdp", "tf": 1}, {"id": "0GNlKuzh7ZJTJ1iigkQEVp", "tf": 1}, {"id": "0kXvGrU1xtobBAkQ1sf2uQ", "tf": 1}, {"id": "0lpkIkav4zSnEWoCtlfyBW", "tf": 1}, {"id": "0mRtoIJczBZFw3ISHr7JIN", "tf": 1}, {"id": "0MVX5xKgWP77Qtvs72gKSG", "tf": 1}, {"id": "0OsYwz3SCLD98IvWfdLeRQ", "tf": 1}, {"id": "0SYRVn2YF7HBscQEmlkpTI", "tf": 1}, {"id": "0T6VlW1YjEskHYnWacdTBP", "tf": 1}, {"id": "0TlLq3lA83rQOYtrqBqSct", "tf": 2}, {"id": "0XpEoWpZqlQpGFYZXDU2Hj", "tf": 1}, {"id": "0yYTOlwMCd08Kb1RIz2FYL", "tf": 1}, {"id": "0yYZso7EcTez67xdRCOrFw", "tf": 1}, {"id": "11cDEev79fPKi6uJCjUhu8", "tf": 1}, {"id": "13JyykwyYQ3T5QxxL34ukQ", "tf": 2}, {"id": "17nGEa20jceT2qypJnTOse", "tf": 1}, {"id": "1AnoNTlYCt1ELWArtKsA4s", "tf": 1}, {"id": "1apzxNzMksJZtbDBKFIsdx", "tf": 1}, {"id": "1boHm9rjmvzxpJASd9dnGK", "tf": 2}, {"id": "1bvuXEOLC95IYvkAtwqREi", "tf": 1}, {"id": "1gqfZG2HORk2sPxoXfnS4y", "tf": 1}, {"id": "1hKdDCpiI9mqz1jVHRKG0E", "tf": 1}, {"id": "1hWrl3T1kIH5b9zRHLfCOn", "tf": 3}, {"id": "1Kjer1JoWuJGNwGV6Pbgv1", "tf": 6}, {"id": "1MxCashpyOjvXfnJ2yiLVW", "tf": 1}, {"id": "1NHEUZMpoReYeWLOICMQyl", "tf": 1}, {"id": "1NtVWYw9QDr30Ei0phACni", "tf": 1}, {"id": "1o6AE0zzRZ9Z4tKVFu9ZDJ", "tf": 1}, {"id": "1ohXrU5DLEfUlfo4tIYbqJ", "tf": 1}, {"id": "1PI87c2lTmkjNUG6EHzvgc", "tf": 1}, {"id": "1Q48AM3uKnWdZEN7UJng6R", "tf": 1}, {"id": "1TWnMN7Cb9HwoI3Ac3DDzo", "tf": 1}, {"id": "1WbMAxHieH1wOCg5WVav9n", "tf": 1}, {"id": "20FZrLl9zSbO9b3DhaqO6M", "tf": 3}, {"id": "20khkbcFHJ63mEJ6nctzcr", "tf": 1}, {"id": "24fdXM8HLxcim9YwQIKrha", "tf": 1}, {"id": "2a9OPIAax8pUKzNZKCxC5L", "tf": 1}, {"id": "2bNbnpiLHz29s0ceWIlX7T", "tf": 1}, {"id": "2ECnUolDjMUwVVwpK2HRyH", "tf": 1}, {"id": "2ij5TPGpAJARUh2HWIdxCx", "tf": 1}, {"id": "2l4Wcuw1Q4TU5iFGthCCHM", "tf": 1}, {"id": "2npw9XuCQpHXM9ramYL4HR", "tf": 1}, {"id": "2nvhlJ4ilhKVSy2Hn5b7ij", "tf": 1}, {"id": "2ORxCzIYVvQYzAUv3iLFfx", "tf": 1}, {"id": "2RcvZFouLOTFZbQHr3nhOj", "tf": 1}, {"id": "2RZ9OA2VzFCRZDng151Yjs", "tf": 1}, {"id": "2U96QtBPJE158fZ74GIqQX", "tf": 1}, {"id": "2Vx8E3K5icPZR7OCklWBXX", "tf": 3}, {"id": "2xmrfQpmS2iJExTlklLoAL", "tf": 1}, {"id": "309z0CzeLvltCqcvpeOD9T", "tf": 1}, {"id": "31UjYv5vLsDkzchJOtUMtW", "tf": 1}, {"id": "32UioUCnMFsr2UN7SvDyXj", "tf": 1}, {"id": "35RN4JojBYBasOZoKcao9D", "tf": 1}, {"id": "386t7MPmZfrV17EbOAMYcj", "tf": 1}, {"id": "3BaridxR3bsmZw3F8ERWPj", "tf": 1}, {"id": "3cHfDtp6kGyfZB10lvZ2Xj", "tf": 1}, {"id": "3dA1Z1MFUVbdY796jNEjr2", "tf": 1}, {"id": "3GUZHOhbl6hQEqsHCkUDDd", "tf": 1}, {"id": "3h2BczCiAjSwHpEyq7UXja", "tf": 1}, {"id": "3H4xY3vJdvjlTtq1YUv0gu", "tf": 1}, {"id": "3Kd7feC47Vwtm0PeC0XBCK", "tf": 1}, {"id": "3kE5NmMUCPLw5sbWxUQToU", "tf": 1}, {"id": "3LcrBMmEejUO09Lrmyixzb", "tf": 1}, {"id": "3MF3HJ5dmKm8SiVKXAsQsR", "tf": 1}, {"id": "3nzga73CbLw9dguYHOwVfI", "tf": 2}, {"id": "3QNo5oDTOSI23CDDpDUE9Q", "tf": 1}, {"id": "3sHuIjfAzluc6S9cXoqfqC", "tf": 1}, {"id": "3u18DwDsN8r88M3Tf0McAc", "tf": 1}, {"id": "3u9fHuAtjMY1RW2mZfO4Cf", "tf": 2}, {"id": "3V8zitLu3UTaYmflW0iCco", "tf": 1}, {"id": "3vFj4xuQTXHOuo6L0qGafv", "tf": 1}, {"id": "3WgHKpcZfkAFzhrhuMTUgX", "tf": 1}, {"id": "3YkDAJzJOJYhxDS4gmbCTt", "tf": 1}, {"id": "3Yzcwfm3sEQaaa3ENFC18h", "tf": 1}, {"id": "49Z4NzrNVES5qz9i4hRguT", "tf": 1}, {"id": "4ewmSyDLQ8Bl3Y6nRQsL7Q", "tf": 1}, {"id": "4iLqG9SeJSnt0cSPICSjxv", "tf": 1}, {"id": "4kqluSwcQs3kqfK82ZrB93", "tf": 1}, {"id": "4Lora6205JbkK6BJlttlRH", "tf": 1}, {"id": "4Q6wWm1GyMweUtoz6PNvrr", "tf": 1}, {"id": "4rr67zXmEYf9ykLigeEsbv", "tf": 1}, {"id": "4st7YJoFrdiQPKMZZ4Nv1l", "tf": 1}, {"id": "4TK1fmhOkCxVXfBGcqGrhz", "tf": 1}, {"id": "4ykIW49ZO7UnmKbancsDIV", "tf": 1}, {"id": "52LaP5RzwlSId81druJ3PC", "tf": 1}, {"id": "537LP4XDgTkF3mfjs7j3Fy", "tf": 1}, {"id": "56JeB4CZ3gQO3cXaI3rFjj", "tf": 1}, {"id": "5fxdGJIIqlcsXFRo0Am1AL", "tf": 1}, {"id": "5ja8KwfwvnFf3Q7AEk4lua", "tf": 1}, {"id": "5JZcX7TTLx4l0xFIXJ3DBt", "tf": 3}, {"id": "5NrgTVSCaBpqJu3Tg7BU6v", "tf": 1}, {"id": "5pY3ovFxbvAg7reGZjJQSp", "tf": 1}, {"id": "5RJ6LmF7ElAfQuCAQ8QDI1", "tf": 1}, {"id": "5rXdcKlk0GXKw3Purh6VTP", "tf": 1}, {"id": "5smFCXEyT3yY3gHnBz02Ql", "tf": 1}, {"id": "5UCWi63ktWEuhOCapRA7c2", "tf": 1}, {"id": "5YxP1CkunbhUQVvctFOHa7", "tf": 1}, {"id": "67ri2FYvHV64JSQTHN98iy", "tf": 1}, {"id": "68fnM4NfYWDxTKghRO0hhP", "tf": 1}, {"id": "6ayCEojiJIe5d8DwXVlGU4", "tf": 1}, {"id": "6bERyJwcB3qHDZMnT6Wy9p", "tf": 1}, {"id": "6GGpso9iwdxajUMNRlPAm5", "tf": 1}, {"id": "6gJb9I7KPf0g3evVOhJhAz", "tf": 1}, {"id": "6hWxL0tpZm0QOLNSpT6Qra", "tf": 1}, {"id": "6JifQymydeuqrgE7KhjHAM", "tf": 1}, {"id": "6K4444NmCw909sumeZS9Ba", "tf": 1}, {"id": "6kig1UFggPUyZBCvXD3Wod", "tf": 4}, {"id": "6LPxzcsPrFEGoTa33gG7QC", "tf": 1}, {"id": "6nBISCOZVQXAWdFIek2QXS", "tf": 1}, {"id": "6NUga6kum23a1B0CP81huS", "tf": 1}, {"id": "6OpHDI8lRiqHLqmUIYUxVr", "tf": 1}, {"id": "6P0Ki6KDNiCo03buu3fYGt", "tf": 1}, {"id": "6pTOqW9WKaSSFBLzp2FVIb", "tf": 1}, {"id": "6rVDypmrk2ub86XUF402uU", "tf": 1}, {"id": "6uebosHeOwzQT3ZBtBCbtu", "tf": 1}, {"id": "6wjSNO6uJYlgbbfauyWhiw", "tf": 1}, {"id": "6ya6FdIQAAwH0b2GkKNFs4", "tf": 1}, {"id": "75UNZ7tjYzsoTMgmpWdzw6", "tf": 1}, {"id": "77yhWjXlpQzmbId8mnZpsZ", "tf": 1}, {"id": "7atm51dFT3BN7vgANsVIeT", "tf": 1}, {"id": "7cqbB8Dxz79PjqsxGaihM3", "tf": 1}, {"id": "7d43We1cl1WMsmUYDMbolv", "tf": 1}, {"id": "7FGq80cy8juXBCD2nrqdWU", "tf": 2}, {"id": "7gRPkCEa3YMaxET5ZYT7Ni", "tf": 1}, {"id": "7gVC9FXLXlMla0p34PEhFI", "tf": 4}, {"id": "7gYtzSmzGgpO0WygzfJroD", "tf": 1}, {"id": "7hvmAHUk63H4JBOQTxUwfx", "tf": 1}, {"id": "7KksdXBhdufqWDxGxyt4I7", "tf": 1}, {"id": "7lIPktnf4GIAT1zl9hhcVD", "tf": 1}, {"id": "7lQWRAjyhTpCWFC0jmclT4", "tf": 4}, {"id": "7noT3FgeH9FbCDLNJODXFP", "tf": 1}, {"id": "7pT6WSg4PCt4mr5ZFyUfsF", "tf": 1}, {"id": "7sjwaBQ6M3aVigYfBjm1sL", "tf": 3}, {"id": "7u57tu5WIpn9YCp6AMBzuG", "tf": 1}], "2300": [{"id": "2hb2C7LOzkXRHbz4d1NapC", "tf": 1}], "230000": [{"id": "05Q5sFIYy6KC887fLw9p1y", "tf": 1}, {"id": "1d6KS9GH06JAd19uiBy9IE", "tf": 1}, {"id": "1RouRzlg8OKFeqc6LvdxmB", "tf": 1}, {"id": "1YXq6U6yY6aQ5dkndki7KC", "tf": 1}, {"id": "3Oe3VdPn6rAueriQvFhCBA", "tf": 1}, {"id": "7egj375ez0KtF3bYCfAHdZ", "tf": 1}], "230007": [{"id": "6ABQcgTtAPCUyMkVwdRNJo", "tf": 1}], "230011": [{"id": "2jQiSYrwJehQAcuaaQrXnS", "tf": 1}], "230013": [{"id": "5U6iZ91dNg5XirDUXWMalJ", "tf": 1}], "230027": [{"id": "13wNEvWmBsWaWVtiLPRIW5", "tf": 1}, {"id": "6FwMGM0Dtmf0vz6BdIc8uP", "tf": 1}], "230039": [{"id": "1ZtG48NtqQdyN1AnXiiYL0", "tf": 1}], "230040": [{"id": "0jT7DDqYbpOik6iun6ydUL", "tf": 1}], "230053": [{"id": "6wtcxwSJs82tpdeIoj93LF", "tf": 1}], "230093": [{"id": "1PB9jyumBYH6jbVpzr3DSs", "tf": 1}, {"id": "4BL79Qie6r0TkXuNQLC8gQ", "tf": 1}], "230113": [{"id": "5mIrFiQO3VwnMK4GAyJOfr", "tf": 1}], "230120": [{"id": "4ejjjAuVya6bapdTjZE9Lx", "tf": 1}, {"id": "4omLxn4XuiHhpwTpO9Yj68", "tf": 1}, {"id": "6SKwQghsR8AISlxhcwyA9R", "tf": 1}], "230133": [{"id": "0i00AL9toLfJeb4VlWLvSi", "tf": 1}, {"id": "3RmKpob8xzv1pzHEQrMJah", "tf": 1}, {"id": "5JgoUSDARCcz9yBhcF7euC", "tf": 1}], "230142": [{"id": "2XAjNdO20yRaXSGARd6fCw", "tf": 1}], "230147": [{"id": "5VarZFY00sO54HErJ3TPCI", "tf": 1}], "230151": [{"id": "6xW2g0c5uSoa3S6xk9eI4j", "tf": 1}], "230156": [{"id": "0xr8RB4uOrqbmpndeoC7rO", "tf": 1}], "230163": [{"id": "6LCrqs85q61pfZCXYvW63B", "tf": 1}], "230173": [{"id": "1qoGmzgGtLrYZOps9UZXml", "tf": 1}], "230185": [{"id": "7bWTJ9aXMNGoQ3rCQEjEWu", "tf": 1}], "230187": [{"id": "7aS6cyqiIzITFwyiOhcepj", "tf": 1}], "230200": [{"id": "4pmc2AxSEq6g7hPVlJCPyP", "tf": 1}], "230213": [{"id": "0TD0ydYJuFPEaqshquDEpw", "tf": 1}], "230227": [{"id": "0prNGof3XqfTvNDxHonvdK", "tf": 1}, {"id": "42ydLwx4i5V49RXHOozJZq", "tf": 1}], "230240": [{"id": "0McI9sOmkpfd4E72njtU0G", "tf": 1}, {"id": "3NitY3eL3TjRvPlQWjaclz", "tf": 1}], "230249": [{"id": "5yfpdBo6QggnG9liGh4PsE", "tf": 1}], "230253": [{"id": "7oVEtyuv9NBmnytsCIsY5I", "tf": 1}], "230260": [{"id": "3vFbJ2n0sNzZG2HCww0BF9", "tf": 1}], "230267": [{"id": "3jxrPXWriZPIXKGbuniXhW", "tf": 1}], "230280": [{"id": "3UI9I3e1g1y5T3SMfdgfGO", "tf": 1}], "230281": [{"id": "0RIHDrcRAXtUlnkvTYPW1a", "tf": 1}], "230288": [{"id": "6U6nzpSvKxju6WA0Kojcxn", "tf": 1}], "230293": [{"id": "6epvwUINain4iSHCTWA0sj", "tf": 1}], "230296": [{"id": "0xsAtU9TemtJgyVnlDNWo3", "tf": 1}], "230320": [{"id": "5CRVwXGikmqzoRO6q7FeAg", "tf": 1}, {"id": "6Rh1rwJagYUEbzoAXtu1LA", "tf": 1}], "230353": [{"id": "6MLHg35rlksBc5OBcdZvJi", "tf": 1}], "230364": [{"id": "0eXU92qkEfIWu4SQOILFU3", "tf": 1}], "230387": [{"id": "7uQ8L9eoeKJPXWG9kG7gFX", "tf": 1}], "230400": [{"id": "3v8QqKguRLsoL93Xpi0feB", "tf": 1}, {"id": "6vWEAOUSxohKxhp0K1BsxL", "tf": 1}], "230413": [{"id": "2hjQWuAy9fsSykGerWU8Wi", "tf": 1}], "230426": [{"id": "2bfGNzdiRa1jXZRdfssSzR", "tf": 1}], "230427": [{"id": "5pRElcsPZrgZXkoON2o5Go", "tf": 1}], "230435": [{"id": "4qkun7AaUFno3rE8xp0zYi", "tf": 1}], "230448": [{"id": "4Hqh0dS4x07zuRw6eBTO7p", "tf": 1}], "230453": [{"id": "5aAx2yezTd8zXrkmtKl66Z", "tf": 1}, {"id": "7MXVkk9YMctZqd1Srtv4MB", "tf": 1}], "230467": [{"id": "2IY7eOUDjw2ArKYxKa2jXc", "tf": 1}, {"id": "37hqGqe1Btdp6xuljIm4zL", "tf": 1}, {"id": "3nFJbZCHP4d9vduKjJLdBL", "tf": 1}, {"id": "7lQqaqZu0vjxzpdATOIsDt", "tf": 1}], "230476": [{"id": "6EDH26ppl7R8oV4tGilCkS", "tf": 1}], "230480": [{"id": "5som7RgLrVXCadUrHxCIIF", "tf": 1}, {"id": "70YvYr2hGlS01bKRIho1HM", "tf": 1}], "230493": [{"id": "546QTayX6j4GcZsfTRrVnL", "tf": 1}, {"id": "7vwkKw2Xd7Pks1X712Au0T", "tf": 1}], "230507": [{"id": "02kdNcUqZRgXwQiYr92gZW", "tf": 1}, {"id": "1XxUDJp9zsjd6tBSvE3la4", "tf": 1}, {"id": "7G6TDmGJXDoBaV6NGj3Yic", "tf": 1}], "230519": [{"id": "3CUz9uazoEvF9kS8rloHGI", "tf": 1}], "230520": [{"id": "0XRjftXFxSo0ZEC0ZdSxWQ", "tf": 1}], "230533": [{"id": "4QKdiLnJ2fnvfLPUldoryF", "tf": 1}], "230551": [{"id": "2jTJ9q2tLYJnElfIkiPwPZ", "tf": 1}], "230560": [{"id": "6rbhWExtuchhpLC5fHnB8n", "tf": 1}], "230568": [{"id": "53UXJ9NlgwfE8oOVFhinrS", "tf": 1}], "230573": [{"id": "3LewMbGqmR4IYtifSNxbGz", "tf": 1}], "230578": [{"id": "69ZaPBHhRMRDjRpW1ivnOU", "tf": 1}], "230580": [{"id": "7wYKvMLMWZz59hlGxLSuxs", "tf": 1}]}